Workbook
Name Accrued_Interest: Overview!$F$13
Name clean_Price: 'Cash Flows'!$C$20
Name Convexity: Valuation!$C$25
Name Coupon_Amount: Overview!$F$6
Name Coupon_Frequency: Overview!$C$9
Name Coupon_Rate: Overview!$C$8
Name Current_Market_Pirce: Overview!$C$12
Name Current_Yield: Valuation!$C$18
Name Current_YTM: Overview!$C$13
Name Day_Count_Conention: Overview!$C$14
Name Days_Accrued: Overview!$F$12
Name Dirty_Price: 'Cash Flows'!$C$18
Name Face_Value: Overview!$C$7
Name Issue_Date: Overview!$C$10
Name Macaulay_Duration: Valuation!$C$20
Name Maturity_Date: Overview!$C$11
Name Modified_Duration: Valuation!$C$21
Name Remaining_Tenor: Overview!$F$8
Name Settlement_Date: Overview!$C$6
Name Total_Duration: 'Cash Flows'!$K$14
Name Total_Present_Value: 'Cash Flows'!$J$14

Sheet Cover

Sheet Overview
A1: CONTROL PANEL – KEY ASSUMPTIONS
B4: 1. KEY ASSUMPTION (INPUTS) | E4: 2. DERIVED / CALCULATED FIELDS (Formula-driven)
B5: Parameter | C5: Value | E5: Parameter | F5: Value
B6: Settlement Date | C6: 46182 | E6: Coupon Amount (₹) | F6: =Face_Value*Coupon_Rate/Coupon_Frequency -> 71.5
B7: Face Value (₹) | C7: 1000 | E7: Original Tenor (yrs) | F7: =YEARFRAC(Issue_Date,Maturity_Date,1) -> 14.997947
B8: Coupon Rate | C8: 0.0715 | E8: Remaining Tenor (yrs) | F8: =YEARFRAC(Settlement_Date,Maturity_Date,1) -> 9.6202091
B9: Coupon Frequency | C9: 1 | E9: Days to Maturity | F9: =C11-C6 -> 3514
B10: Issue Date | C10: 44218 | E10: Last Coupon Date | F10: =COUPPCD(Settlement_Date,Maturity_Date,1,3) -> 46044
B11: Maturity Date | C11: 49696 | E11: Next Coupon Date | F11: =COUPNCD(Settlement_Date,Maturity_Date,1,3) -> 46409
B12: Current Market Price (₹) | C12: 1028.93 | E12: Days Accrued | F12: =C6-F10 -> 138
B13: Current YTM (Base) | C13: 0.0775 | E13: Accrued Interest (Rs) | F13: =Face_Value*Coupon_Rate*Days_Accrued/365 -> 27.032877
B14: Day Count Convention | C14: ACT/365
B15: Credit Rating | C15: AAA / Stable
B16: 10Y G-Sec Yield | C16: 0.0697
B17: AAA Corp 10Y Low | C17: 0.075
B18: AAA Corp 10Y High | C18: 0.085

Sheet Bond Data
B1: BOND INFORMATION DASHBOARD – INE134E07AT8
B4: 1. Structural Features | E4: 2. Market & Yield Metrics (as at Settlement)
B5: Issuer | C5: Power Finance Corporation Ltd | E5: Settlement Date | F5: =Settlement_Date -> 46182
B6: ISIN | C6: INE134E07AT8 | E6: Remaining Tenor (yrs) | F6: =Overview!F8 -> 9.6202091
B7: BSE Symbol | C7: 715PFCL36 | E7: Current YTM | F7: =Current_YTM -> 0.0775
B8: Instrument Type | C8: Secured, Rated, Listed NCD | E8: Dirty Price (₹) | F8: =Dirty_Price -> 986.43289
B9: Seniority | C9: Senior Secured | E9: Accrued Interest (₹) | F9: =Accrued_Interest -> 27.032877
B10: Security | C10: Asset coverage for principal + interest | E10: Clean Price (₹) | F10: =clean_Price -> 959.40001
B11: Face Value (₹) | C11: =Face_Value -> 1000 | E11: Current Yield | F11: =Current_Yield -> 0.074525744
B12: Issue Date | C12: =Issue_Date -> 44218 | E12: Macaulay Duration (yrs) | F12: =Macaulay_Duration -> 7.0408061
B13: Maturity Date | C13: =Maturity_Date -> 49696 | E13: Modified Duration (yrs) | F13: =Modified_Duration -> 6.5343909
B14: Original Tenor | C14: =TEXT(Overview!F7,"0.00")&" years" -> 15.00 years | E14: DV01 (₹ per ₹1,000 FV) | F14: =Valuation!C23 -> 0.64457381
B15: Outstanding Issue | C15: ₹1,330.05 crore (Series VII Tranche I) | E15: Convexity | F15: =Convexity -> 57.891941
B16: Put / Call Options | C16: None – Bullet Maturity | E16: Spread vs G-Sec (bps) | F16: =(Overview!$C$13-Overview!C16)*10000 -> 78
B17: Tax Status | C17: Taxable NCD (TDS applicable) | E17: Spread vs AAA Low (bps) | F17: =(Overview!$C$13-Overview!C17)*10000 -> 25
B18: NRI Eligible | C18: Yes | E18: Spread vs AAA High (bps) | F18: =(Overview!$C$13-Overview!C18)*10000 -> -75
B19: Listing | C19: BSE Listed | E19: Domestic Rating | F19: CARE AAA / ICRA AAA / Stable
B20: Day Count | C20: =Overview!C14 -> ACT/365 | E20: International Rating | F20: Fitch BBB- / Moody's Baa3 / Stable

Sheet Cash Flows
B1: CASH FLOW SCHEDULE
B3: # | C3: Payment Date | D3: Days from Sett. | E3: Year Fraction | F3: Coupon (₹) | G3: Principal (₹) | H3: Total CF (₹) | I3: Discount Factor | J3: Present Value (₹) | K3: Weight (Duration) | L3: Convexity Weight
B4: 1 | C4: 46409 | D4: =C4-Overview!$C$6 -> 227 | E4: =D4/365 -> 0.62191781 | F4: =Overview!$C$7*Overview!$C$8 -> 71.5 | G4: =0 -> 0 | H4: =F4+G4 -> 71.5 | I4: =1/(1+Overview!$C$13)^E4 -> 0.95463888 | J4: =H4*I4 -> 68.25668 | K4: =E4*J4 -> 42.450045 | L4: =E4*(E4+1)*J4 -> 68.850483
B5: 2 | C5: 46774 | D5: =C5-Overview!$C$6 -> 592 | E5: =D5/365 -> 1.6219178 | F5: =Overview!$C$7*Overview!$C$8 -> 71.5 | G5: =0 -> 0 | H5: =F5+G5 -> 71.5 | I5: =1/(1+Overview!$C$13)^E5 -> 0.88597576 | J5: =H5*I5 -> 63.347267 | K5: =E5*J5 -> 102.74406 | L5: =E5*(E5+1)*J5 -> 269.38648
B6: 3 | C6: 47140 | D6: =C6-Overview!$C$6 -> 958 | E6: =D6/365 -> 2.6246575 | F6: =Overview!$C$7*Overview!$C$8 -> 71.5 | G6: =0 -> 0 | H6: =F6+G6 -> 71.5 | I6: =1/(1+Overview!$C$13)^E6 -> 0.82208315 | J6: =H6*I6 -> 58.778945 | K6: =E6*J6 -> 154.2746 | L6: =E6*(E6+1)*J6 -> 559.19259
B7: 4 | C7: 47505 | D7: =C7-Overview!$C$6 -> 1323 | E7: =D7/365 -> 3.6246575 | F7: =Overview!$C$7*Overview!$C$8 -> 71.5 | G7: =0 -> 0 | H7: =F7+G7 -> 71.5 | I7: =1/(1+Overview!$C$13)^E7 -> 0.7629542 | J7: =H7*I7 -> 54.551225 | K7: =E7*J7 -> 197.72951 | L7: =E7*(E7+1)*J7 -> 914.43126
B8: 5 | C8: 47870 | D8: =C8-Overview!$C$6 -> 1688 | E8: =D8/365 -> 4.6246575 | F8: =Overview!$C$7*Overview!$C$8 -> 71.5 | G8: =0 -> 0 | H8: =F8+G8 -> 71.5 | I8: =1/(1+Overview!$C$13)^E8 -> 0.70807814 | J8: =H8*I8 -> 50.627587 | K8: =E8*J8 -> 234.13525 | L8: =E8*(E8+1)*J8 -> 1316.9306
B9: 6 | C9: 48235 | D9: =C9-Overview!$C$6 -> 2053 | E9: =D9/365 -> 5.6246575 | F9: =Overview!$C$7*Overview!$C$8 -> 71.5 | G9: =0 -> 0 | H9: =F9+G9 -> 71.5 | I9: =1/(1+Overview!$C$13)^E9 -> 0.65714909 | J9: =H9*I9 -> 46.98616 | K9: =E9*J9 -> 264.28106 | L9: =E9*(E9+1)*J9 -> 1750.7715
B10: 7 | C10: 48601 | D10: =C10-Overview!$C$6 -> 2419 | E10: =D10/365 -> 6.6273973 | F10: =Overview!$C$7*Overview!$C$8 -> 71.5 | G10: =0 -> 0 | H10: =F10+G10 -> 71.5 | I10: =1/(1+Overview!$C$13)^E10 -> 0.60975843 | J10: =H10*I10 -> 43.597728 | K10: =E10*J10 -> 288.93946 | L10: =E10*(E10+1)*J10 -> 2203.8561
B11: 8 | C11: 48966 | D11: =C11-Overview!$C$6 -> 2784 | E11: =D11/365 -> 7.6273973 | F11: =Overview!$C$7*Overview!$C$8 -> 71.5 | G11: =0 -> 0 | H11: =F11+G11 -> 71.5 | I11: =1/(1+Overview!$C$13)^E11 -> 0.5659011 | J11: =H11*I11 -> 40.461928 | K11: =E11*J11 -> 308.6192 | L11: =E11*(E11+1)*J11 -> 2662.5805
B12: 9 | C12: 49331 | D12: =C12-Overview!$C$6 -> 3149 | E12: =D12/365 -> 8.6273973 | F12: =Overview!$C$7*Overview!$C$8 -> 71.5 | G12: =0 -> 0 | H12: =F12+G12 -> 71.5 | I12: =1/(1+Overview!$C$13)^E12 -> 0.52519823 | J12: =H12*I12 -> 37.551674 | K12: =E12*J12 -> 323.97321 | L12: =E12*(E12+1)*J12 -> 3119.0188
B13: 10 | C13: 49696 | D13: =C13-Overview!$C$6 -> 3514 | E13: =D13/365 -> 9.6273973 | F13: =Overview!$C$7*Overview!$C$8 -> 71.5 | G13: =Overview!$C$7 -> 1000 | H13: =F13+G13 -> 1071.5 | I13: =1/(1+Overview!$C$13)^E13 -> 0.48742296 | J13: =H13*I13 -> 522.2737 | K13: =E13*J13 -> 5028.1364 | L13: =E13*(E13+1)*J13 -> 53436.003
B14: TOTAL | F14: =SUM(F4:F13) -> 715 | G14: =SUM(G4:G13) -> 1000 | H14: =SUM(H4:H13) -> 1715 | J14: =SUM(J4:J13) -> 986.43289 | K14: =SUM(K4:K13) -> 6945.2828 | L14: =SUM(L4:L13) -> 66301.021
B17: VALUATION SUMMARY
B18: Dirty Price (₹) | C18: =SUM(J4:J13) -> 986.43289
B19: Accrued Interest (₹) | C19: =Accrued_Interest -> 27.032877
B20: Clean Price (₹) | C20: =C18-C19 -> 959.40001
B21: Dirty Price Check | C21: =IF(ROUND(C18,2)=ROUND(C19+C20,2),"PASS","FAIL") -> PASS

Sheet Valuation
B1: BOND VALUATION – FULL ANALYTICS
B3: A) Manual / DCF Method | E3: B) Excel Built-in Functions | H3: MODEL ERROR CHECKS
B4: Metric | C4: Value | E4: Metric | F4: Value | H4: Check | I4: Result
B5: Face Value (₹) | C5: =Face_Value -> 1000 | E5: Clean Price (PRICE) | F5: =PRICE(Settlement_Date,Maturity_Date,Coupon_Rate,Current_YTM,100,1,3)*Face_Value/100 -> 959.70656 | H5: Check 1: PV of CF = Dirty Price | I5: =IF(ROUND(SUM('Cash Flows'!J4:J13),2)=ROUND(Dirty_Price,2),"PASS","FAIL") -> PASS
B6: Coupon Rate | C6: =Coupon_Rate -> 0.0715 | E6: YTM (YIELD) | F6: =YIELD(Settlement_Date,Maturity_Date,Coupon_Rate,clean_Price/Face_Value*100,100,1,3) -> 0.077547579 | H6: Check 2: Dirty − AI = Clean | I6: =IF(ROUND(Dirty_Price,2)=ROUND(clean_Price+Accrued_Interest,2),"PASS","FAIL") -> PASS
B7: YTM (Base) | C7: =Current_YTM -> 0.0775 | E7: Macaulay Duration | F7: =DURATION(Settlement_Date,Maturity_Date,Coupon_Rate,Current_YTM,1,3) -> 7.0370989 | H7: Check 3: ModD < MacD | I7: =IF(C21<C20,"PASS","FAIL") -> PASS
B8: Settlement Date | C8: =Settlement_Date -> 46182 | E8: Modified Duration | F8: =MDURATION(Settlement_Date,Maturity_Date,Coupon_Rate,Current_YTM,1,3) -> 6.5309502 | H8: Check 4: Yield↑ → Price↓ | I8: =IF(PRICE(Settlement_Date,Maturity_Date,Coupon_Rate,Current_YTM+0.001,100,1,3)<PRICE(Settlement_Date,Maturity_Date,Coupon_Rate,Current_YTM-0.001,100,1,3),"PASS","FAIL") -> PASS
B9: Maturity Date | C9: =Maturity_Date -> 49696 | E9: Accrued Interest | F9: =Overview!C7*Overview!C8*Overview!F12/365 -> 27.032877 | H9: Check 5: CF Total Principal = FV | I9: =IF(ROUND(SUM('Cash Flows'!G4:G13),2)=ROUND(Face_Value,2),"PASS","FAIL") -> PASS
B10: Remaining Tenor | C10: =Remaining_Tenor -> 9.6202091
B12: Dirty Price (₹) | C12: =Dirty_Price -> 986.43289
B13: Last Coupon Date | C13: =Overview!F10 -> 46044
B14: Days Accrued | C14: =Days_Accrued -> 138
B15: Accrued Interest (₹) | C15: =Accrued_Interest -> 27.032877
B16: Clean Price (₹) | C16: =clean_Price -> 959.40001
B18: Current Yield | C18: =Face_Value*Coupon_Rate/C16 -> 0.074525744
B20: Macaulay Duration (yrs) | C20: =Total_Duration/Total_Present_Value -> 7.0408061
B21: Modified Duration (yrs) | C21: =Macaulay_Duration/(1+Current_YTM) -> 6.5343909
B22: Dollar Duration (₹) | C22: =Modified_Duration*Dirty_Price/100 -> 64.457381
B23: DV01 / PVBP (₹ per bps) | C23: =Modified_Duration*Dirty_Price/10000 -> 0.64457381
B24: PVBP = DV01 (₹) | C24: =C23 -> 0.64457381
B25: Convexity | C25: ='Cash Flows'!L14/((1+Current_YTM)^2*Dirty_Price) -> 57.891941

Sheet Sensitivity
B1: INTEREST RATE SENSITIVITY ANALYSIS
B3: Scenario | C3: Yield Shock (bps) | D3: New YTM (%) | E3: Bond Price (₹) | F3: Price Change (₹) | G3: % Price Change | H3: Duration Approx Price | I3: Dur+Conv Approx Price | J3: Convexity Contribution (₹)
B4: -200 bps | C4: -200 | D4: =Current_YTM+C4/10000 -> 0.0575 | E4: =PRICE(Settlement_Date,Maturity_Date,Coupon_Rate,D4,100,1,3)*Face_Value/100 -> 1100.8301 | F4: =E4-clean_Price -> 141.43007 | G4: =F4/clean_Price -> 0.14741512 | H4: =clean_Price*(1-Modified_Duration*(C4/10000)) -> 1084.7819 | I4: =clean_Price*(1-Modified_Duration*(C4/10000)+0.5*Convexity*(C4/10000)^2) -> 1095.8902 | J4: =clean_Price*0.5*Convexity*(C4/10000)^2 -> 11.108306
B5: -150 bps | C5: -150 | D5: =Current_YTM+C5/10000 -> 0.0625 | E5: =PRICE(Settlement_Date,Maturity_Date,Coupon_Rate,D5,100,1,3)*Face_Value/100 -> 1063.134 | F5: =E5-clean_Price -> 103.73394 | G5: =F5/clean_Price -> 0.10812376 | H5: =clean_Price*(1-Modified_Duration*(C5/10000)) -> 1053.4364 | I5: =clean_Price*(1-Modified_Duration*(C5/10000)+0.5*Convexity*(C5/10000)^2) -> 1059.6849 | J5: =clean_Price*0.5*Convexity*(C5/10000)^2 -> 6.248422
B6: -100 bps | C6: -100 | D6: =Current_YTM+C6/10000 -> 0.0675 | E6: =PRICE(Settlement_Date,Maturity_Date,Coupon_Rate,D6,100,1,3)*Face_Value/100 -> 1027.1033 | F6: =E6-clean_Price -> 67.703248 | G6: =F6/clean_Price -> 0.07056832 | H6: =clean_Price*(1-Modified_Duration*(C6/10000)) -> 1022.091 | I6: =clean_Price*(1-Modified_Duration*(C6/10000)+0.5*Convexity*(C6/10000)^2) -> 1024.868 | J6: =clean_Price*0.5*Convexity*(C6/10000)^2 -> 2.7770765
B7: -50 bps | C7: -50 | D7: =Current_YTM+C7/10000 -> 0.0725 | E7: =PRICE(Settlement_Date,Maturity_Date,Coupon_Rate,D7,100,1,3)*Face_Value/100 -> 992.65393 | F7: =E7-clean_Price -> 33.253914 | G7: =F7/clean_Price -> 0.034661157 | H7: =clean_Price*(1-Modified_Duration*(C7/10000)) -> 990.74549 | I7: =clean_Price*(1-Modified_Duration*(C7/10000)+0.5*Convexity*(C7/10000)^2) -> 991.43976 | J7: =clean_Price*0.5*Convexity*(C7/10000)^2 -> 0.69426912
B8: BASE | C8: 0 | D8: =Current_YTM+C8/10000 -> 0.0775 | E8: =PRICE(Settlement_Date,Maturity_Date,Coupon_Rate,D8,100,1,3)*Face_Value/100 -> 959.70656 | F8: =E8-clean_Price -> 0.30654956 | G8: =F8/clean_Price -> 0.00031952216 | H8: =clean_Price*(1-Modified_Duration*(C8/10000)) -> 959.40001 | I8: =clean_Price*(1-Modified_Duration*(C8/10000)+0.5*Convexity*(C8/10000)^2) -> 959.40001 | J8: =clean_Price*0.5*Convexity*(C8/10000)^2 -> 0
B9: +50 bps | C9: 50 | D9: =Current_YTM+C9/10000 -> 0.0825 | E9: =PRICE(Settlement_Date,Maturity_Date,Coupon_Rate,D9,100,1,3)*Face_Value/100 -> 928.18617 | F9: =E9-clean_Price -> -31.21384 | G9: =F9/clean_Price -> -0.03253475 | H9: =clean_Price*(1-Modified_Duration*(C9/10000)) -> 928.05454 | I9: =clean_Price*(1-Modified_Duration*(C9/10000)+0.5*Convexity*(C9/10000)^2) -> 928.74881 | J9: =clean_Price*0.5*Convexity*(C9/10000)^2 -> 0.69426912
B10: +100 bps | C10: 100 | D10: =Current_YTM+C10/10000 -> 0.0875 | E10: =PRICE(Settlement_Date,Maturity_Date,Coupon_Rate,D10,100,1,3)*Face_Value/100 -> 898.0219 | F10: =E10-clean_Price -> -61.378114 | G10: =F10/clean_Price -> -0.06397552 | H10: =clean_Price*(1-Modified_Duration*(C10/10000)) -> 896.70907 | I10: =clean_Price*(1-Modified_Duration*(C10/10000)+0.5*Convexity*(C10/10000)^2) -> 899.48614 | J10: =clean_Price*0.5*Convexity*(C10/10000)^2 -> 2.7770765
B11: +150 bps | C11: 150 | D11: =Current_YTM+C11/10000 -> 0.0925 | E11: =PRICE(Settlement_Date,Maturity_Date,Coupon_Rate,D11,100,1,3)*Face_Value/100 -> 869.14676 | F11: =E11-clean_Price -> -90.25325 | G11: =F11/clean_Price -> -0.094072596 | H11: =clean_Price*(1-Modified_Duration*(C11/10000)) -> 865.36359 | I11: =clean_Price*(1-Modified_Duration*(C11/10000)+0.5*Convexity*(C11/10000)^2) -> 871.61202 | J11: =clean_Price*0.5*Convexity*(C11/10000)^2 -> 6.248422
B12: +200 bps | C12: 200 | D12: =Current_YTM+C12/10000 -> 0.0975 | E12: =PRICE(Settlement_Date,Maturity_Date,Coupon_Rate,D12,100,1,3)*Face_Value/100 -> 841.49745 | F12: =E12-clean_Price -> -117.90257 | G12: =F12/clean_Price -> -0.12289198 | H12: =clean_Price*(1-Modified_Duration*(C12/10000)) -> 834.01812 | I12: =clean_Price*(1-Modified_Duration*(C12/10000)+0.5*Convexity*(C12/10000)^2) -> 845.12643 | J12: =clean_Price*0.5*Convexity*(C12/10000)^2 -> 11.108306
B15: DV01 / PVBP Reference
B16: Metric | C16: Value
B17: DV01 (₹ per ₹1,000 FV) | C17: =Valuation!C23 -> 0.64457381
B18: Modified Duration | C18: =Valuation!C21 -> 6.5343909

Sheet Scenarios
B1: SCENARIO ANALYSIS (1-Year Holding Period)
B4: 1. Scenario Assumptions
B5: Assumption | C5: Bull | D5: Base | E5: Bear
B6: YTM in 1 Year (%) | C6: 0.0575 | D6: =Current_YTM -> 0.0775 | E6: 0.0875
B7: Entry Clean Price (₹) | C7: =Valuation!$C$16 -> 959.40001 | D7: =Valuation!$C$16 -> 959.40001 | E7: =Valuation!$C$16 -> 959.40001
B10: 2. Scenario Results
B11: Return Component | C11: Bull | D11: Base | E11: Bear
B12: Exit Clean Price (₹) | C12: =PRICE(Settlement_Date+365,Maturity_Date,Coupon_Rate,C6,100,1,3)*Face_Value/100 -> 1092.6548 | D12: =PRICE(Settlement_Date+365,Maturity_Date,Coupon_Rate,D6,100,1,3)*Face_Value/100 -> 962.6323 | E12: =PRICE(Settlement_Date+365,Maturity_Date,Coupon_Rate,E6,100,1,3)*Face_Value/100 -> 905.16029
B13: Coupon Income (₹) | C13: =Face_Value*Coupon_Rate -> 71.5 | D13: =Face_Value*Coupon_Rate -> 71.5 | E13: =Face_Value*Coupon_Rate -> 71.5
B14: Capital Gain / (Loss) (₹) | C14: =C12-clean_Price -> 133.25476 | D14: =D12-clean_Price -> 3.2322837 | E14: =E12-clean_Price -> -54.239719
B15: Total Return (₹) | C15: =C13+C14 -> 204.75476 | D15: =D13+D14 -> 74.732284 | E15: =E13+E14 -> 17.260281
B16: 1-Year Holding Period Return (%) | C16: =C15/clean_Price -> 0.21341959 | D16: =D15/clean_Price -> 0.077894812 | E16: =E15/clean_Price -> 0.017990703

Sheet Credit Risk
B1: PFC CREDIT DASHBOARD – 5-YEAR FINANCIAL TREND (Consolidated)
B3: Income Statement (₹ Crore, Consolidated)
B4: Metric | C4: FY22 | D4: FY23 | E4: FY24 | F4: FY25 | G4: FY26(TTM) | H4: CAGR (FY22-26)
B5: Interest Income (₹ cr) | C5: 76262 | D5: 77807 | E5: 91508 | F5: 107106 | G5: 115444 | H5: =_xlfn.RRI(4,C5,G5) -> 0.10921515
B6: YoY | D6: =D5/C5-1 -> 0.020259107 | E6: =E5/D5-1 -> 0.17608955 | F6: =F5/E5-1 -> 0.17045504 | G6: =G5/F5-1 -> 0.077848113
B7: Financing Profit (₹ cr) | C7: 23338 | D7: 26501 | E7: 33573 | F7: 38603 | G7: 42848 | H7: =_xlfn.RRI(4,C7,G7) -> 0.16403685
B8: YoY | D8: =D7/C7-1 -> 0.13553004 | E8: =E7/D7-1 -> 0.26685785 | F8: =F7/E7-1 -> 0.14982277 | G8: =G7/F7-1 -> 0.10996555
B9: PBT (₹ cr) | C9: 23382 | D9: 26496 | E9: 33588 | F9: 38632 | G9: 42850 | H9: =_xlfn.RRI(4,C9,G9) -> 0.16350242
B10: YoY | D10: =D9/C9-1 -> 0.13317937 | E10: =E9/D9-1 -> 0.26766304 | F10: =F9/E9-1 -> 0.15017268 | G10: =G9/F9-1 -> 0.1091841
B11: PAT (₹ cr) | C11: 18768 | D11: 21179 | E11: 26461 | F11: 30514 | G11: 33625 | H11: =_xlfn.RRI(4,C11,G11) -> 0.15694063
B12: YoY | D12: =D11/C11-1 -> 0.12846334 | E12: =E11/D11-1 -> 0.24939799 | F12: =F11/E11-1 -> 0.15316881 | G12: =G11/F11-1 -> 0.1019532
B13: EPS | C13: 42.47 | D13: 48.15 | E13: 59.88 | F13: 69.67 | G13: 78.49 | H13: =_xlfn.RRI(4,C13,G13) -> 0.1659583
B14: YoY | D14: =D13/C13-1 -> 0.13374146 | E14: =E13/D13-1 -> 0.24361371 | F14: =F13/E13-1 -> 0.16349365 | G14: =G13/F13-1 -> 0.12659681
B17: Balance Sheet (₹ Crore, Consolidated)
B18: Metric | C18: FY22 | D18: FY23 | E18: FY24 | F18: FY25 | G18: FY26 (TTM) | H18: CAGR
B19: Equity Capital (₹ cr) | C19: 2640 | D19: 2640 | E19: 3300 | F19: 3300 | G19: 3300 | H19: =_xlfn.RRI(4,C19,G19) -> 0.057371263
B20: YoY | D20: =D19/C19-1 -> 0 | E20: =E19/D19-1 -> 0.25 | F20: =F19/E19-1 -> 0 | G20: =G19/F19-1 -> 0
B21: Reserves (₹ cr) | C21: 69036 | D21: 81518 | E21: 97847 | F21: 114438 | G21: 129561 | H21: =_xlfn.RRI(4,C21,G21) -> 0.17044138
B22: YoY | D22: =D21/C21-1 -> 0.18080422 | E22: =E21/D21-1 -> 0.20031159 | F22: =F21/E21-1 -> 0.16956064 | G22: =G21/F21-1 -> 0.13215016
B23: Net Worth (₹ cr) | C23: =C19+C21 -> 71676 | D23: =D19+D21 -> 84158 | E23: =E19+E21 -> 101147 | F23: =F19+F21 -> 117738 | G23: =G19+G21 -> 132861
B24: Total Borrowings (₹ cr) | C24: 660476 | D24: 751158 | E24: 861961 | F24: 971758 | G24: 1012503 | H24: =_xlfn.RRI(4,C24,G24) -> 0.11271725
B25: YoY | D25: =D24/C24-1 -> 0.13729795 | E25: =E24/D24-1 -> 0.14750958 | F25: =F24/E24-1 -> 0.12738047 | G25: =G24/F24-1 -> 0.041929163
B26: Total Assets (₹ cr) | C26: 791000 | D26: 896112 | E26: 1038877 | F26: 1178086 | G26: 1244579 | H26: =_xlfn.RRI(4,C26,G26) -> 0.11998317
B27: YoY | D27: =D26/C26-1 -> 0.13288496 | E27: =E26/D26-1 -> 0.15931602 | F27: =F26/E26-1 -> 0.1339995 | G27: =G26/F26-1 -> 0.05644155
B28: Debt / Equity | C28: =C24/C23 -> 9.2147441 | D28: =D24/D23 -> 8.9255686 | E28: =E24/E23 -> 8.5218642 | F28: =F24/F23 -> 8.253563 | G28: =G24/G23 -> 7.6207691
B29: Loan Assets – Standalone (₹ cr) | C29: 373388 | D29: 432312 | E29: 481353 | F29: 543120 | G29: 574018 | H29: =_xlfn.RRI(4,C29,G29) -> 0.11350274
D30: =D29/C29-1 -> 0.15780904 | E30: =E29/D29-1 -> 0.11343891 | F30: =F29/E29-1 -> 0.12831955 | G30: =G29/F29-1 -> 0.056889822
B32: Asset Quality & Capital Adequacy
B33: Metric | C33: FY21 | D33: FY22 | E33: FY23 | F33: FY24 | G33: FY25 | H33: 9M FY26 | I33: Trend
B34: Gross Stage 3 (GNPA) Ratio – Consolidated | C34: 0.0739 | D34: 0.0561 | E34: 0.0391 | F34: 0.0302 | G34: 0.0194 | H34: 0.0126 | I34: =AVERAGE(C34:H34) -> 0.03855
B35: Net NPA Ratio – Consolidated | C35: 0.0209 | D35: 0.028 | E35: 0.0103 | F35: 0.0085 | G35: 0.0038 | H35: 0.0026 | I35: =AVERAGE(C35:H35) -> 0.01235
B36: Capital Adequacy Ratio (CAR) – Standalone | C36: 0.1883 | D36: 0.2351 | E36: 0.244 | F36: 0.2541 | G36: 0.2208 | H36: 0.22 | I36: =AVERAGE(C36:H36) -> 0.22705
B37: Return on Equity (RoE) – Consolidated | C37: 0.21 | D37: 0.21 | E37: 0.2 | F37: 0.21 | G37: 0.21 | H37: 0.21 | I37: =AVERAGE(C37:H37) -> 0.20833333
B38: Return on Total Assets (RoTA) – Standalone | C38: 0.0224 | D38: 0.0255 | E38: 0.0277 | F38: 0.0302 | G38: 0.032 | H38: 0.0335 | I38: =AVERAGE(C38:H38) -> 0.02855
B39: On-Book Gearing (x) – Standalone | C39: 6.36 | D39: 5.52 | E39: 5.43 | F39: 5.26 | G39: 5.23 | H39: 4.85 | I39: =AVERAGE(C39:H39) -> 5.4416667
B40: Net Interest Margin (NIM) – Standalone | C40: 0.0407 | D40: 0.0427 | E40: 0.0409 | F40: 0.0402 | G40: 0.0445 | H40: 0.044 | I40: =AVERAGE(C40:H40) -> 0.042166667
B42: Helper coloumn | C42: 0.15 | D42: =C42 -> 0.15 | E42: =D42 -> 0.15 | F42: =E42 -> 0.15 | G42: =F42 -> 0.15 | H42: =G42 -> 0.15

Sheet Relative Valuation
B1: RELATIVE VALUE ANALYSIS – PFC vs PEERS
B4: Instrument | C4: Rating | D4: Maturity | E4: Coupon | F4: Indicative YTM | G4: Spread vs G-Sec (bps) | H4: Spread vs PFC Bond (bps) | I4: Relative Valuation
B5: GoI 10Y G-Sec | C5: Sovereign | D5: 2035 | E5: 0.0648 | F5: 0.069134 | G5: - | H5: - | I5: N/A
B6: PFC 7.15% 2036 (This Bond) | C6: AAA | D6: 22-Jan-2036 | E6: =Coupon_Rate -> 0.0715 | F6: =Current_YTM -> 0.0775 | G6: =(F6-$F$5)*10000 -> 83.66 | H6: 0 | I6: BASE
B7: Other PFC INR 2031-38 | C7: AAA | D7: ~2031-38 | E7: ~6.95%-7.55% | F7: 0.0739 | G7: =(F7-$F$5)*10000 -> 47.66 | H7: =(F7-F6)*10000 -> -36 | I7: =IF(F7>F6,"Wider / Cheaper",IF(F7=F6,"PAR","Tighter / Richer")) -> Tighter / Richer
B8: REC 54EC 5Y Bonds | C8: AAA | D8: 5Y | E8: 0.05 | F8: 0.0513 | G8: =(F8-$F$5)*10000 -> -178.34 | H8: =(F8-F6)*10000 -> -262 | I8: =IF(F8>F6,"Wider / Cheaper",IF(F8=F6,"PAR","Tighter / Richer")) -> Tighter / Richer
B9: NABARD AAA Bonds | C9: AAA | D9: ~10Y-15Y | E9: ~7.04%-7.64%c | F9: 0.063 | G9: =(F9-$F$5)*10000 -> -61.34 | H9: =(F9-F6)*10000 -> -145 | I9: =IF(F9>F6,"Wider / Cheaper",IF(F9=F6,"PAR","Tighter / Richer")) -> Tighter / Richer
B10: Generic AAA Corp 10Y | C10: AAA | D10: ~10Y | E10: — | F10: 0.08 | G10: =(F10-$F$5)*10000 -> 108.66 | H10: =(F10-F6)*10000 -> 25 | I10: =IF(F10>F6,"Wider / Cheaper",IF(F10=F6,"PAR","Tighter / Richer")) -> Wider / Cheaper
B13: RELATIVE VALUE CONCLUSION
B15: At the current indicative YTM of 7.75%, the PFC 2036 bond offers a solid risk premium, trading at a spread of +83.66 bps over the 10Y G-Sec. When compared to its peers, this specific bond looks highly attractive It offers an extra 35 bps over other PFC curves and significantly outperforms high grade PSU peers like REC 54EC and NABARD. While generic private AAA corporate 10Y bonds yield slightly higher (+25 bps), they carry higher private credit risk. VALUATION CONCLUSION: Given PFC’s strong sovereign backing and robust credit metrics, this bond offers an excellent yield pickup over risk free benchmarks. It is highly recommended as a safe, high yielding carry asset for a long term buy and hold portfolio.

Sheet Risk Review
B1: RISK DASHBOARD – BOND & ISSUER RISK ASSESSMENT
B3: Risk Factor | C3: Level | D3: Score (1-5) | E3: Weight (%) | F3: Key Metrics / Rationale | K3: Mitigants
B4: Credit Risk | C4: LOW | D4: 1 | E4: 0.1 | F4: One of the biggest concerns for investors is whether the company might face repayment problems. In PFC's case, that risk appears to be low. The company's bad loans (NPA) are below 0.5% and it maintains a capital adequacy ratio of 22%, which is well above regulatory requirements. In addition, the Government of India owns about 56% of the company, providing further confidence in its stability. | K4: The government is the company's majority shareholder and it plays a critical role in financing India's power sector. Because of its strategic importance and strong government backing, investors generally view it as a highly secure institution. This is one of the imp reasons why it has received the highest AAA credit rating.
B5: Interest Rate Risk | C5: MEDIUM-HIGH | D5: 4 | E5: 0.2 | F5: Bond prices move up and down when market interest rates change, such as FD rates or lending rates. Since this bond has a relatively long maturity of about 10 years, it is more sensitive to interest rate changes. As a result, if the RBI increases interest rates by 1%, the bond's market value could decline by approximately 6.5%. | K5: This price fluctuation only matters if you plan to sell the bond before maturity. If your intention is to hold the bond for the full 10 years, there is no need to worry about daily market price movements. You will continue to receive your fixed interest payments on time every year and at maturity, you will receive the bond's principal amount as well.
B6: Liquidity Risk | C6: MEDIUM | D6: 3 | E6: 0.1 | F6: If you suddenly need money and have to sell the bond before maturity, finding a buyer may not always be easy. Unlike stocks, this bond does not trade very actively on the exchange. As a result, you may need to sell it through brokers or in the over the counter (OTC) market, where transactions are often arranged directly between buyers and sellers. | K6: PFC is a large and well established issuer in the bond market. If you ever need to sell the bond, your broker can usually find a buyer, such as a mutual fund, insurance company or bank. While the bond may not trade as frequently as stocks, the risk of being unable to sell it is generally low because of PFC's strong reputation and market presence.
B7: Reinvestment Risk | C7: LOW-MEDIUM | D7: 2 | E7: 0.05 | F7: Every year, you will receive ₹71.50 as interest from the bond. However, when you reinvest that money, interest rates in the market may be lower than they are today. If that happens, you may earn a lower return on those interest payments, which can reduce your overall investment return. | K7: This is a common risk in all fixed income investments. The good news is that your principal amount is protected and you have already locked in the current interest rate for the next 10 years As a result, even if reinvestment rates fall in the future, the impact is usually manageable, since the majority of your return still comes from the bond's fixed coupon payments.
B8: Inflation Risk | C8: LOW-MEDIUM | D8: 2 | E8: 0.05 | F8: Current inflation is approximately 3.5% (CPI Apr 26), while the bond offers a yield of around 7.5%, providing a meaningful positive real return and helping preserve purchasing power. | K8: The RBI has kept inflation under control in recent years. As long as inflation does not rise sharply from current levels, the bond's yield should continue to provide a reasonable return after accounting for inflation.
B9: Regulatory / Policy Risk | C9: MEDIUM | D9: 3 | E9: 0.15 | F9: Since PFC is a financial company (NBFC), changes in RBI regulations could affect its business. If the RBI introduces stricter rules in the future, it could limit PFC's lending activities or increase its compliance and operating costs. | K9: PFC plays an important role in financing power projects across India and has strong government support. Because of its strategic importance to the country's power sector, investors generally expect the company to receive supportive policy treatment and regulatory backing when needed. As a result, the risk of regulations severely harming PFC's business is often considered relatively low.
B10: Power-Sector / Credit Concentration Risk | C10: MEDIUM | D10: 3 | E10: 0.2 | F10: This is probably the bond's most important underlying risk. Around 75% of PFC's loan portfolio is linked to State DISCOMs. Many DISCOMs face financial challenges because they often sell electricity at subsidized rates and struggle to recover their full costs. As a result, PFC is exposed to the financial health and repayment ability of these power distribution companies. | K10: The risk is partly mitigated by government initiatives such as RDSS, which seek to improve DISCOM liquidity and payment performance. Furthermore, PFC's growing focus on financing private renewable energy projects provides greater diversification and supports the long-term quality of its loan portfolio.
B11: PSU / Sovereign-Link Risk | C11: LOW-MEDIUM | D11: 2 | E11: 0.05 | F11: As a government-backed company, PFC may sometimes face pressure to support public policy objectives. This could include providing loans to financially weaker power utilities on terms that may be less attractive from a purely commercial perspective. In such situations, business decisions may occasionally be influenced by policy goals, which could affect profitability. | K11: PFC has a strong track record of operating profitably and paying dividends to the government. As the majority shareholder, the government's interests are generally aligned with maintaining the company's financial strength, making the risk of value-destructive decisions relatively low.
B12: Extension / Duration Drift Risk | C12: MEDIUM | D12: 3 | E12: 0.1 | F12: Could the company repay the bond before the 10-year maturity date, or extend the maturity date to avoid making payments? For the bond, the answer depends on the bond's terms. If the bond does not have a call option or any provision allowing the issuer to extend the maturity, then PFC must continue making coupon payments and repay the principal on the scheduled maturity date. | K12: This risk is very low, as the bond has a bullet maturity structure with no call or put options. The maturity date is fixed, and investors are expected to receive regular coupon payments along with full principal repayment in January 2036. This provides a high degree of certainty regarding cash flows and repayment timing.
B15: RISK PROFILE SCORE
B16: Risk Score | C16: =SUMPRODUCT(D4:D12,E4:E12) -> 2.85 | D16: =IF(C16<2,"LOW RISK",IF(C16<3,"LOW-MODERATE RISK",IF(C16<3.5,"MODERATE RISK",IF(C16<4.25,"MODERATE-HIGH RISK","HIGH RISK")))) -> LOW-MODERATE RISK
B17: Note: Score 1 = Very Low Risk; 5 = Very Risk Risk

Sheet DASHBOARD
B1: BOND ANALYTICS DASHBOARD
B3: Yield Shock Curve (Price Vs Yield) | K3: Holding Period Return (1Y)
B21: Asset Quality Trend | K21: Asset Quality Trend
