Workbook

Sheet Cover Page
B10: DCF Valuation & Analysis
B12: Forecasting Future Cash Flows.
B13: Estimating Intrinsic Value.
B15: WORKBOOK NAVIGATION
B21: 1 | E21: 2 | H21: 3 | K21: 4 | N21: 5 | Q21: 6 | T21: 7
B22: ASSUMPTIONS | E22: MANAGEMENT TRACKER | H22: FINANCIAL STATEMENT | K22: COST OF CAPITAL (WACC) | N22: DCF VALUATION | Q22: SENSITIVITY ANALYSIS | T22: FOOTBALL FIELD ANALYSIS

Sheet Assumptions
B1: LARSEN & TOUBRO — KEY ASSUMPTIONS & RESEARCH NOTES
B2: Metrics | C2: Historical Avg | D2: 24 | E2: =D2+1 -> 25 | F2: =E2+1 -> 26 | G2: =F2+1 -> 27 | H2: =G2+1 -> 28 | I2: =H2+1 -> 29 | J2: =I2+1 -> 30
B4: REVENUE DRIVERS & ORDER BOOK
B5: Group Revenue (₹ Cr) | D5: 221113 | E5: 255734 | F5: 285874 | G5: =F5*(1+G6) -> 317320.14 | H5: =G5*(1+H6) -> 358571.76 | I5: =H5*(1+I6) -> 408771.8 | J5: =I5*(1+J6) -> 468043.72
B6: YoY Revenue Growth % | C6: 0.149 | D6: 0.206 | E6: =E5/D5-1 -> 0.15657605 | F6: =F5/E5-1 -> 0.11785684 | G6: 0.11 | H6: 0.13 | I6: 0.14 | J6: 0.145
B7: P&M Revenue (₹ Cr) | D7: 175000 | E7: 199000 | F7: 219000 | G7: =F7*(1+G9) -> 243090 | H7: =G7*(1+H9) -> 272260.8 | I7: =H7*(1+I9) -> 304932.1 | J7: =I7*(1+J9) -> 341523.95
B8: Order Book (₹ Cr) | D8: 578000 | E8: 621000 | F8: 740000
B9: Order Inflow Growth % | C9: 0.17 | E9: =E8/D8-1 -> 0.074394464 | F9: =F8/E8-1 -> 0.19162641 | G9: 0.11 | H9: 0.12 | I9: 0.12 | J9: 0.12
B10: EBITDA (Cr) | D10: 0.13 | E10: 0.13 | F10: 0.12 | G10: 0.12 | H10: 0.125 | I10: 0.13 | J10: 0.135
B12: COST STRUCTURE & MARGIN ASSUMPTIONS
B13: Material Cost % of Revenue | C13: 0.338 | D13: 0.345 | E13: 0.36 | F13: 0.335 | G13: 0.335 | H13: 0.33 | I13: 0.325 | J13: 0.32
B14: Employee Cost % of Revenue | C14: 0.185 | D14: 0.186 | E14: 0.183 | F14: 0.183 | G14: 0.185 | H14: 0.185 | I14: 0.18 | J14: 0.175
B15: Other Operating cost (%) Revenue | C15: 0.048 | D15: 0.0483 | E15: 0.0391 | F15: 0.0445 | G15: 0.045 | H15: 0.044225 | I15: 0.04320625 | J15: 0.044232812
B16: Depreciation % of Revenue | C16: 0.016 | D16: 0.017 | E16: 0.016 | F16: 0.015 | G16: 0.016 | H16: 0.017 | I16: 0.017 | J16: 0.018
B17: Capex % of Revenue | C17: 0.019 | D17: 0.02 | E17: 0.017 | F17: 0.017 | G17: 0.025 | H17: 0.028 | I17: 0.028 | J17: 0.025
B18: Effective Tax Rate % | C18: 0.25 | D18: 0.24 | E18: 0.25 | F18: 0.26 | G18: 0.255 | H18: 0.255 | I18: 0.255 | J18: 0.255
B19: Net Working Capital % of Revenue | C19: -0.01 | D19: -0.044 | E19: -0.13 | F19: -0.094 | G19: 0.1 | H19: 0.08 | I19: 0.07 | J19: 0.06
B21: TERMINAL VALUE ASSUMPTIONS
B23: Assumption | C23: Value | E23: Working Note:
B24: Terminal Growth Rate (g) | C24: 0.055 | E24: NWC | F24: =F5*F19 -> -26872.156 | G24: =G5*G19 -> 31732.014 | H24: =H5*H19 -> 28685.741 | I24: =I5*I19 -> 28614.026 | J24: =J5*J19 -> 28082.623
B25: Terminal EBITDA Margin | C25: 0.105 | E25: Change in Nwc | G25: =G24-F24 -> 58604.17 | H25: =H24-G24 -> -3046.2733 | I25: =I24-H24 -> -71.714352 | J25: =J24-I24 -> -531.40335
B26: EV/EBITDA Exit Multiple (cross-check) | C26: 14

Sheet Mgmt Tracker
B1: MANAGEMENT CREDIBILITY TRACKER — L&T FY24–FY26
B2: Metric | C2: Year | D2: Guidance | E2: Actual | F2: Hit/Miss
B3: Revenue Growth | C3: FY26 | D3: 0.15 | E3: =Assumptions!F6 -> 0.11785684 | F3: MISS
B4: Revenue Growth | C4: FY25 | D4: 0.15 | E4: =Assumptions!E6 -> 0.15657605 | F4: MEET
B5: Revenue Growth | C5: FY24 | D5: 0.15 | E5: =Assumptions!D6 -> 0.206 | F5: BEAT
B6: Order Inflow Growth | C6: FY26 | D6: 0.1 | E6: ~22%+ | F6: BEAT
B7: Order Inflow Growth | C7: FY25 | D7: 10–15% | E7: ~18%+ | F7: BEAT
B8: P&M EBITDA Margin | C8: FY26 | D8: +20bps | E8: −30bps | F8: MISS
B9: P&M EBITDA Margin | C9: FY25 | D9: 0.085 | E9: 0.083 | F9: NEAR MISS
B10: ROE Target | C10: FY26 | D10: 18% (Lakshya26) | E10: 15.5% (adj 16.6%) | F10: MISS
B11: NWC/Revenue | C11: FY26 | D11: 12% | E11: 4.1% | F11: BEAT
B12: Revenue Guidance (FY27) | C12: FY27 | D12: 10-12% | E12: — | F12: PENDING
B13: Order Inflow (FY27) | C13: FY27 | D13: 10-12% | E13: — | F13: PENDING
B14: ROE (Lakshya 31) | C14: FY31 | D14: 16-17% | E14: — | F14: PENDING
B17: VERDICT
B19: L&T has a STRONG TRACK record of winning new orders and has often received more orders than management initially expected. The company also has a large order book, which provides good visibility for future revenue. However, revenue growth and margins have not always been consistent. At times, results have been affected by project execution issues and external factors. In FY26, the weaker performance was mainly due to temporary external challenges rather than any major problem with the business itself. Because of this, I prefer to use reasonable and balanced assumptions for future growth and margins instead of relying completely on management guidance. I also take a slightly conservative approach because the company has not always achieved some of its long-term profitability targets, such as ROE.

Sheet Income Statement
B1: LARSEN & TOUBRO — CONSOLIDATED INCOME STATEMENT (₹ Crore)
B2: Particulars ₹ Crore | C2: 23 | D2: =C2+1 -> 24 | E2: =D2+1 -> 25 | F2: =E2+1 -> 26 | G2: =Assumptions!G2 -> 27 | H2: =Assumptions!H2 -> 28 | I2: =Assumptions!I2 -> 29 | J2: =Assumptions!J2 -> 30
B3: Net Revenue / Gross Revenue | C3: 183341 | D3: 221113 | E3: 255734 | F3: 285874 | G3: =F3*(1+G4) -> 317320.14 | H3: =G3*(1+H4) -> 358571.76 | I3: =H3*(1+I4) -> 408771.8 | J3: =I3*(1+J4) -> 468043.72
B4: YoY Growth % | D4: =(D3-C3)/C3 -> 0.20602048 | E4: =(E3-D3)/D3 -> 0.15657605 | F4: =(F3-E3)/E3 -> 0.11785684 | G4: =Assumptions!G6 -> 0.11 | H4: =Assumptions!H6 -> 0.13 | I4: =Assumptions!I6 -> 0.14 | J4: =Assumptions!J6 -> 0.145
B5: Material & Subcontracting | C5: 60128 | D5: 76341 | E5: 92173 | F5: 97683 | G5: =G3*G6 -> 106302.25 | H5: =H3*H6 -> 118328.68 | I5: =I3*I6 -> 132850.84 | J5: =J3*J6 -> 149773.99
B6: % of Revenue | C6: =C5/C3 -> 0.32795719 | D6: =D5/D3 -> 0.34525785 | E6: =E5/E3 -> 0.36042529 | F6: =F5/F3 -> 0.34169949 | G6: =Assumptions!G13 -> 0.335 | H6: =Assumptions!H13 -> 0.33 | I6: =Assumptions!I13 -> 0.325 | J6: =Assumptions!J13 -> 0.32
B7: Employee Costs | C7: 37230 | D7: 41171 | E7: 46773 | F7: 52219 | G7: =G8*G3 -> 58704.226 | H7: =H8*H3 -> 66335.775 | I7: =I8*I3 -> 73578.925 | J7: =J8*J3 -> 81907.65
B8: % of Revenue | C8: =C7/C3 -> 0.20306424 | D8: =D7/D3 -> 0.18619891 | E8: =E7/E3 -> 0.18289707 | F8: =F7/F3 -> 0.18266439 | G8: =Assumptions!G14 -> 0.185 | H8: =Assumptions!H14 -> 0.185 | I8: =Assumptions!I14 -> 0.18 | J8: =Assumptions!J14 -> 0.175
B9: Manufacturing & Other Opex | C9: 50293 | D9: 64182 | E9: 72337 | F9: 89828 | G9: =G3-G13-G5-G7-G11 -> 99955.844 | H9: =H3-H13-H5-H7-H11 -> 113228 | I9: =I3-I13-I5-I7-I11 -> 131540.21 | J9: =J3-J13-J5-J7-J11 -> 152473.28
B10: % of Revenue | C10: =C9/C3 -> 0.27431398 | D10: =D9/D3 -> 0.29026787 | E10: =E9/E3 -> 0.28286032 | F10: =F9/F3 -> 0.31422235 | G10: =G9/G3 -> 0.315 | H10: =H9/H3 -> 0.315775 | I10: =I9/I3 -> 0.32179375 | J10: =J9/J3 -> 0.32576719
B11: Other Operating Expenses | C11: 8525 | D11: 10688 | E11: 9993 | F11: 12715 | G11: =G12*G3 -> 14279.406 | H11: =H12*H3 -> 15857.836 | I11: =I12*I3 -> 17661.497 | J11: =J12*J3 -> 20702.89
B12: % of Revenue | C12: =C11/C3 -> 0.046498056 | D12: =D11/D3 -> 0.048337276 | E12: =E11/E3 -> 0.039075758 | F12: =F11/F3 -> 0.044477637 | G12: =Assumptions!G15 -> 0.045 | H12: =Assumptions!H15 -> 0.044225 | I12: =Assumptions!I15 -> 0.04320625 | J12: =Assumptions!J15 -> 0.044232812
B13: EBITDA | C13: 27165 | D13: 28731 | E13: 34458 | F13: 33429 | G13: =G14*G3 -> 38078.417 | H13: =H14*H3 -> 44821.47 | I13: =I14*I3 -> 53140.335 | J13: =J14*J3 -> 63185.902
B14: EBITDA Margin % | C14: =C13/C3 -> 0.14816653 | D14: =D13/D3 -> 0.12993809 | E14: =E13/E3 -> 0.13474157 | F14: =F13/F3 -> 0.11693613 | G14: =Assumptions!G10 -> 0.12 | H14: =Assumptions!H10 -> 0.125 | I14: =Assumptions!I10 -> 0.13 | J14: =Assumptions!J10 -> 0.135
B15: Depreciation & Amortisation | C15: 3502 | D15: 3682 | E15: 4121 | F15: 4365 | G15: =G3*Assumptions!G16 -> 5077.1222 | H15: =H3*Assumptions!H16 -> 6095.7199 | I15: =I3*Assumptions!I16 -> 6949.1207 | J15: =J3*Assumptions!J16 -> 8424.7869
B16: EBIT | C16: =C13-C15 -> 23663 | D16: =D13-D15 -> 25049 | E16: =E13-E15 -> 30337 | F16: =F13-F15 -> 29064 | G16: =G13-G15 -> 33001.295 | H16: =H13-H15 -> 38725.75 | I16: =I13-I15 -> 46191.214 | J16: =J13-J15 -> 54761.115
B17: EBIT Margin % | C17: =C16/C3 -> 0.12906551 | D17: =D16/D3 -> 0.11328597 | E17: =E16/E3 -> 0.11862717 | F17: =F16/F3 -> 0.10166717 | G17: =G16/G3 -> 0.104 | H17: =H16/H3 -> 0.108 | I17: =I16/I3 -> 0.113 | J17: =J16/J3 -> 0.117
B18: Other Income | C18: 2891 | D18: 4953 | E18: 3198 | F18: 4986 | G18: 5500 | H18: 6200 | I18: 7000 | J18: 8000
B19: Finance Costs / Interest | C19: 9445 | D19: 9512 | E19: 9925 | F19: 10056 | G19: 10500 | H19: 11000 | I19: 10500 | J19: 10000
B20: Profit Before Tax (PBT) | C20: =C16+C18-C19 -> 17109 | D20: =D16+D18-D19 -> 20490 | E20: =E16+E18-E19 -> 23610 | F20: =F16+F18-F19 -> 23994 | G20: =G16+G18-G19 -> 28001.295 | H20: =H16+H18-H19 -> 33925.75 | I20: =I16+I18-I19 -> 42691.214 | J20: =J16+J18-J19 -> 52761.115
B21: PBT Margin % | C21: =C20/C3 -> 0.093317916 | D21: =D20/D3 -> 0.09266755 | E21: =E20/E3 -> 0.092322491 | F21: =F20/F3 -> 0.083932082 | G21: =G20/G3 -> 0.088243042 | H21: =H20/H3 -> 0.094613558 | I21: =I20/I3 -> 0.10443777 | J21: =J20/J3 -> 0.11272689
B22: Tax Expense | C22: 4578 | D22: 4918 | E22: 5900 | F22: 6238 | G22: =G20*G23 -> 7140.3301 | H22: =H20*H23 -> 8651.0662 | I22: =I20*I23 -> 10886.26 | J22: =J20*J23 -> 13454.084
B23: Effective Tax Rate % | C23: =C22/C20 -> 0.26757847 | D23: =D22/D20 -> 0.24001952 | E23: =E22/E20 -> 0.24989411 | F23: =F22/F20 -> 0.25998166 | G23: =Assumptions!G18 -> 0.255 | H23: =Assumptions!H18 -> 0.255 | I23: =Assumptions!I18 -> 0.255 | J23: =Assumptions!J18 -> 0.255
B24: PAT (Total) | C24: =C20-C22 -> 12531 | D24: =D20-D22 -> 15572 | E24: =E20-E22 -> 17710 | F24: =F20-F22 -> 17756 | G24: =G20-G22 -> 20860.964 | H24: =H20-H22 -> 25274.684 | I24: =I20-I22 -> 31804.954 | J24: =J20-J22 -> 39307.031
B25: Minority Interest / NCI | C25: 2060 | D25: 2488 | E25: 2636 | F25: 2870 | G25: 3300 | H25: 3795 | I25: 4365 | J25: 5020
B26: PAT Attributable to Owners | C26: =C24-C25 -> 10471 | D26: =D24-D25 -> 13084 | E26: =E24-E25 -> 15074 | F26: =F24-F25 -> 14886 | G26: =G24-G25 -> 17560.964 | H26: =H24-H25 -> 21479.684 | I26: =I24-I25 -> 27439.954 | J26: =J24-J25 -> 34287.031
B27: PAT Margin % | C27: =C26/C3 -> 0.057112157 | D27: =D26/D3 -> 0.059173364 | E27: =E26/E3 -> 0.058944059 | F27: =F26/F3 -> 0.052071892 | G27: =G26/G3 -> 0.055341475 | H27: =H26/H3 -> 0.059903445 | I27: =I26/I3 -> 0.067127806 | J27: =J26/J3 -> 0.073256043
B29: EPS (₹) — Basic | C29: =C26/C30 -> 76.119511 | D29: =D26/D30 -> 95.114859 | E29: =E26/E30 -> 109.58127 | F29: =F26/F30 -> 108.2146 | G29: =G26/G30 -> 127.6604 | H29: =H26/H30 -> 156.14774 | I29: =I26/I30 -> 199.47626 | J29: =J26/J30 -> 249.25146
B30: Shares Outstanding (Cr) | C30: 137.56 | D30: 137.56 | E30: 137.56 | F30: 137.56 | G30: 137.56 | H30: 137.56 | I30: 137.56 | J30: 137.56

Sheet WACC
B1: WACC COMPUTATION — LARSEN & TOUBRO
B3: 1. COST OF EQUITY — CAPM
B4: Particulars | C4: Values
B5: Risk Free Rate (Rf) | C5: 0.079
B6: Beta (β) | C6: 1.22
B7: Equity Risk Premium (ERP) | C7: 0.062
B8: Size / Illiquidity Premium | C8: 0
B9: Cost of Equity (Ke) | C9: =C5+C6*C7+C8 -> 0.15464
B11: 2. COST OF DEBT
B12: Particulars | C12: Values
B13: Total Borrowings (₹ Cr) | C13: 125497
B14: Interest Expense (₹ Cr) | C14: 10056
B15: Pre-tax Cost of Debt (Kd) | C15: =C14/C13 -> 0.080129405
B16: Effective Tax Rate | C16: 0.255
B17: After tax Cost of Debt (Kd) | C17: =C15*(1-C16) -> 0.059696407
B19: 3. CAPITAL STRUCTURE
B20: Particulars | C20: Values
B21: Market Cap | C21: ='Income Statement'!F30*3927 -> 540198.12
B22: Cash | C22: 20848
B23: Net Debt (₹ Cr) | C23: =C13-C22 -> 104649
B24: Enterprise Value Proxy (₹ Cr) | C24: =C21+C13-C22 -> 644847.12
B25: Weight of Equity (We) | C25: =C21/C24 -> 0.83771502
B26: Weight of Debt (Wd) | C26: =1-C25 -> 0.16228498
B28: 4. WACC
B29: WACC | C29: =C25*C9+C26*C17 -> 0.13923208
B31: PEER BENCHMARKING NOTE
B32: L&T WACC of 13.9% is consistent with peer EPC / infrastructure conglomerates in India. Siemens India Ke est. ~14%, WACC ~12-13% (lower leverage). ABB India Ke est. ~14.5%, WACC ~13.5%. L&T's higher financial services leverage marginally elevates WACC vs pure EPC peers.

Sheet DCF Valuation
B1: LARSEN & TOUBRO — DCF VALUATION (₹ Crore, except per share figures)
B3: WACC | C3: =Sensitivity!J6 -> 0.13923208
B4: Terminal Growth Rate | C4: =Sensitivity!J7 -> 0.055
B5: Exit EV/EBITDA Multiple | C5: =Sensitivity!J16 -> 14
B7: ₹ Crore | C7: FY27E | D7: FY28E | E7: FY29E | F7: FY30E
B8: FREE CASH FLOW TO FIRM (FCFF) — PROJECTION
B9: EBIT | C9: ='Income Statement'!G16 -> 33001.295 | D9: ='Income Statement'!H16 -> 38725.75 | E9: ='Income Statement'!I16 -> 46191.214 | F9: ='Income Statement'!J16 -> 54761.115
B10: Less: Tax on EBIT (25.5%) | C10: =C9*'Income Statement'!G23 -> 8415.3301 | D10: =D9*'Income Statement'!H23 -> 9875.0662 | E10: =E9*'Income Statement'!I23 -> 11778.76 | F10: =F9*'Income Statement'!J23 -> 13964.084
B11: NOPAT (Net Operating PAT) | C11: =C9-C10 -> 24585.964 | D11: =D9-D10 -> 28850.684 | E11: =E9-E10 -> 34412.454 | F11: =F9-F10 -> 40797.031
B12: Add: Depreciation & Amort. | C12: ='Income Statement'!G15 -> 5077.1222 | D12: ='Income Statement'!H15 -> 6095.7199 | E12: ='Income Statement'!I15 -> 6949.1207 | F12: ='Income Statement'!J15 -> 8424.7869
B13: Less: Capital Expenditure | C13: ='Income Statement'!G3*Assumptions!G17 -> 7933.0035 | D13: ='Income Statement'!H3*Assumptions!H17 -> 10040.009 | E13: ='Income Statement'!I3*Assumptions!I17 -> 11445.611 | F13: ='Income Statement'!J3*Assumptions!J17 -> 11701.093
B14: Less: Δ Net Working Capital | C14: =Assumptions!G25 -> 58604.17 | D14: =Assumptions!H25 -> -3046.2733 | E14: =Assumptions!I25 -> -71.714352 | F14: =Assumptions!J25 -> -531.40335
B15: Free Cash Flow to Firm (FCFF) | C15: =C11+C12-C13-C14 -> -36874.087 | D15: =D11+D12-D13-D14 -> 27952.668 | E15: =E11+E12-E13-E14 -> 29987.679 | F15: =F11+F12-F13-F14 -> 38052.128
B17: Discounting
B18: Period (Mid-year Convention) | C18: 0.5 | D18: 1.5 | E18: 2.5 | F18: 3.5
B19: WACC | C19: =$C$3 -> 0.13923208 | D19: =$C$3 -> 0.13923208 | E19: =$C$3 -> 0.13923208 | F19: =$C$3 -> 0.13923208
B20: PV of FCFF | C20: =C15/(1+C19)^C18 -> -34547.384 | D20: =D15/(1+D19)^D18 -> 22988.199 | E20: =E15/(1+E19)^E18 -> 21647.729 | F20: =F15/(1+F19)^F18 -> 24112.166
B22: Terminal Value
B23: Terminal FCFF (FY30E × (1+g)) | F23: =F15*(1+$C$4) -> 40144.995
B24: Terminal Growth Rate (g) | F24: =Assumptions!C24 -> 0.055
B25: Gordon Growth TV = TF÷(WACC−g) | F25: =F23/($C$3-$C$4) -> 476599.82
B26: PV of Terminal Value | F26: =F25/(1+$C$3)^4 -> 282946.97
B28: ENTERPRISE VALUE → EQUITY VALUE BRIDGE | E28: EV/EBITDA Method
B29: Sum of PV(FCFF) — Explicit Period | C29: =SUM(C20:F20) -> 34200.71 | E29: Cross-check: EV/EBITDA Exit (14x) | F29: ='Income Statement'!J13*C5 -> 884602.62 | G29: =Sensitivity!J15 -> 0.13923208
B30: PV of Terminal Value (Gordon) | C30: =F26 -> 282946.97 | E30: PV of EV/EBITDA Terminal Value | F30: =F29/(1+G29)^4 -> 525169.38 | G30: =Sensitivity!J16 -> 14
B31: Enterprise Value (EV) | C31: =C29+C30 -> 317147.68 | E31: Sum of PV(FCFF) — Explicit Period | F31: =C29 -> 34200.71
B32: Less: Net Debt (Debt − Cash) | C32: =WACC!C23 -> 104649 | E32: Less: Net Debt (Debt − Cash) | F32: =C32 -> 104649
B33: Less: Minority Interest (NCI) | C33: 19240.66 | E33: Less: Minority Interest (NCI) | F33: =C33 -> 19240.66
B34: Add: Investments / Assoc. Value | C34: 68377 | E34: Add: Investments / Assoc. Value | F34: =C34 -> 68377
B35: Equity Value (Owners) | C35: =C31-C32-C33+C34 -> 261635.02 | E35: Equity Value (Owners) | F35: =F30+F31-F32-F33+F34 -> 503857.43
B37: Shares Outstanding (Cr) | C37: ='Income Statement'!F30 -> 137.56 | E37: Shares Outstanding (Cr) | F37: =C37 -> 137.56
B38: IMPLIED SHARE PRICE (₹) | C38: =C35/C37 -> 1901.9702 | E38: IMPLIED SHARE PRICE (₹) | F38: =F35/F37 -> 3662.8194
B39: Current Market Price (₹) | C39: 3927 | E39: Current Market Price (₹) | F39: 3927
B40: Upside / (Downside) % | C40: =C38/C39-1 -> -0.5156684 | E40: Upside / (Downside) % | F40: =F38/F39-1 -> -0.067272891
B42: Target Share Price (Blended) | C42: =(C38*50%)+(F38*50%) -> 2782.3948
B45: ENTERPRISE VALUE (₹ Cr) | E45: =C31 -> 317147.68
B46: EQUITY VALUE (₹ Cr) | E46: =C35 -> 261635.02
B47: IMPLIED SHARE PRICE (₹) | E47: =C38 -> 1901.9702
B48: CURRENT PRICE (₹) | E48: =C39 -> 3927
B49: UPSIDE / DOWNSIDE | E49: =C38/C39-1 -> -0.5156684

Sheet Sensitivity
B1: SENSITIVITY ANALYSIS — IMPLIED SHARE PRICE (₹)
B3: Table 1: Implied Share Price — WACC vs Terminal Growth Rate (g)
B5: WACC | C5: Growth Rate
C6: ='DCF Valuation'!C38 -> 1901.9702 | D6: 0.045 | E6: 0.05 | F6: 0.055 | G6: 0.06 | H6: 0.065 | J6: =WACC!C29 -> 0.13923208 | K6: For Sensitivity Table (Note: Don’t do anything with this cells)'
C7: 0.129 | D7: 1973.5339 | E7: 2118.3672 | F7: 2282.7727 | G7: 2471.005 | H7: 2688.6486 | J7: =Assumptions!C24 -> 0.055
C8: 0.134 | D8: 1814.4068 | E8: 1941.2737 | F8: 2084.1997 | G8: 2246.44 | H8: 2432.1934
C9: 0.13923208 | D9: 1666.2625 | E9: 1777.5125 | F9: 1901.9702 | G9: 2042.1358 | H9: 2201.1836
C10: 0.144 | D10: 1545.1358 | E10: 1644.4052 | F10: 1754.8285 | G10: 1878.3975 | H10: 2017.6081
C11: 0.149 | D11: 1430.2703 | E11: 1518.8284 | F11: 1616.8076 | G11: 1725.7956 | H11: 1847.7584
B13: Table 1: Implied Share Price — WACC vs Exit EV/EBITDA Multiple
B15: Growth Rate | J15: =WACC!C29 -> 0.13923208 | K15: For Sensitivity Table (Note: Don’t do anything with this cells)'
B16: WACC | C16: ='DCF Valuation'!F38 -> 3662.8194 | D16: 12 | E16: 13 | F16: 14 | G16: 15 | H16: 16 | J16: =Assumptions!C26 -> 14
C17: 0.129 | D17: 3237.6782 | E17: 3520.3954 | F17: 3803.1126 | G17: 4085.8298 | H17: 4368.547
C18: 0.134 | D18: 3178.2384 | E18: 3456.0023 | F18: 3733.7662 | G18: 4011.5301 | H18: 4289.294
C19: 0.13923208 | D19: 3117.4268 | E19: 3390.1231 | F19: 3662.8194 | G19: 3935.5156 | H19: 4208.2119
C20: 0.144 | D20: 3063.2133 | E20: 3331.3918 | F20: 3599.5703 | G20: 3867.7488 | H20: 4135.9273
C21: 0.149 | D21: 3007.5615 | E21: 3271.1024 | F21: 3534.6432 | G21: 3798.184 | H21: 4061.7248
C23: LEGEND: | D23: ≥₹4,000 (Strong Buy)
D24: ₹3,500–₹4,000 (Hold/Fair Value)
D25: <3,500 (Sell/Overvalued)

Sheet Football Field Summary
B2: FOOTBALL FIELD — VALUATION RANGE SUMMARY
B3: Methodology | F3: Low (₹) | G3: High (₹) | H3: Helper Column
B4: DCF — Bear Case | F4: =Sensitivity!D11 -> 1430.2703 | G4: =Sensitivity!E10 -> 1644.4052 | H4: =G4-F4 -> 214.13487
B5: DCF — Base Case | F5: =Sensitivity!E9 -> 1777.5125 | G5: =Sensitivity!G9 -> 2042.1358 | H5: =G5-F5 -> 264.6233
B6: DCF — Bull Case | F6: =Sensitivity!G7 -> 2471.005 | G6: =Sensitivity!H7 -> 2688.6486 | H6: =G6-F6 -> 217.6436
B7: EV/EBITDA (13.0x - 15.0x) | F7: =Sensitivity!E19 -> 3390.1231 | G7: =Sensitivity!G19 -> 3935.5156 | H7: =G7-F7 -> 545.39254
B8: 52-Week Range | F8: 3288 | G8: 4400 | H8: =G8-F8 -> 1112
