Workbook

Sheet COVER
B2: STRICTLY CONFIDENTIAL
B4: TORRENT PHARMA LTD.
B7: Proposed Acquisition of
B8: JB CHEMICALS & PHARMACEUTICULS LTD.
B12: F I N A N C I A L M O D E L
C14: Assumptions & Operating Drivers
C16: Standalone Financial Model — Torrent Pharma
C18: Standalone Financial Model — JB Chemicals
C20: Revenue & Cost Synergies
C22: Deal Structure Analysis
C24: Pro Forma Merger Financials
C26: EPS Accretion / Dilution Analysis
C28: Integrated Valuation Framework
C30: Football Field Valuation Summary
B32: Date: 22 MAY 2026

Sheet Assumptions
B1: M&A FINANCIAL MODEL — ASSUMPTIONS (DRIVER BASED)
B2: Torrent Pharmaceuticals acquiring J.B. Chemicals & Pharmaceuticals | ₹ Crores
A4: # | B4: Metric | C4: FY23A | D4: FY24A | E4: FY25A | F4: FY26E | G4: FY27E | H4: FY28E | I4: FY29E | J4: FY30E
B5: J.B. CHEMICALS — KEY DRIVERS (INPUTS ONLY — CHANGE HERE)
B6: Revenue Growth % (YoY) | C6: - | D6: 0.1063 | E6: 0.1245 | F6: 0.12 | G6: 0.13 | H6: 0.13 | I6: 0.11 | J6: 0.1
B7: Gross Margin % | C7: 0.628 | D7: 0.66 | E7: 0.664 | F7: 0.67 | G7: 0.675 | H7: 0.68 | I7: 0.682 | J7: 0.684
B8: EBITDA Margin % | C8: 0.221 | D8: 0.27 | E8: 0.277 | F8: 0.285 | G8: 0.29 | H8: 0.295 | I8: 0.298 | J8: 0.3
B9: D&A as % of Revenue | C9: 0.0362 | D9: 0.0396 | E9: 0.0437 | F9: 0.043 | G9: 0.042 | H9: 0.041 | I9: 0.041 | J9: 0.04
B10: CapEx as % of Revenue | C10: 0.243 | D10: 0.075 | E10: 0.031 | F10: 0.032 | G10: 0.032 | H10: 0.031 | I10: 0.03 | J10: 0.028
B11: Net Working Capital as % of Revenue | C11: 0.27 | D11: 0.261 | E11: 0.299 | F11: 0.3 | G11: 0.295 | H11: 0.29 | I11: 0.285 | J11: 0.28
B12: Interest Expense (Cr) — JB standalone | C12: 36 | D12: 44 | E12: 12 | F12: 8 | G12: 6 | H12: 5 | I12: 5 | J12: 5
B13: Effective Tax Rate % | C13: 0.258 | D13: 0.261 | E13: 0.259 | F13: 0.258 | G13: 0.258 | H13: 0.258 | I13: 0.258 | J13: 0.258
B15: J.B. CHEMICALS — DERIVED FINANCIALS (Formula-calculated from drivers above)
B16: Revenue (Cr) | C16: 3149 | D16: 3484 | E16: 3918 | F16: =E16*(1+F6) -> 4388.16 | G16: =F16*(1+G6) -> 4958.6208 | H16: =G16*(1+H6) -> 5603.2415 | I16: =H16*(1+I6) -> 6219.5981 | J16: =I16*(1+J6) -> 6841.5579
B17: Gross Profit (Cr) | C17: 1978 | D17: 2299 | E17: 2602 | F17: =F16*F7 -> 2940.0672 | G17: =G16*G7 -> 3347.069 | H17: =H16*H7 -> 3810.2042 | I17: =I16*I7 -> 4241.7659 | J17: =J16*J7 -> 4679.6256
B18: EBITDA (Cr) | C18: 696 | D18: 939 | E18: 1087 | F18: =F16*F8 -> 1250.6256 | G18: =G16*G8 -> 1438 | H18: =H16*H8 -> 1652.9562 | I18: =I16*I8 -> 1853.4402 | J18: =J16*J8 -> 2052.4674
B19: D&A (Cr) | C19: 114 | D19: 138 | E19: 171 | F19: =F16*F9 -> 188.69088 | G19: =G16*G9 -> 208.26207 | H19: =H16*H9 -> 229.7329 | I19: =I16*I9 -> 255.00352 | J19: =J16*J9 -> 273.66232
B20: EBIT (Cr) | C20: =C18-C19 -> 582 | D20: =D18-D19 -> 801 | E20: =E18-E19 -> 916 | F20: =F18-F19 -> 1061.9347 | G20: =G18-G19 -> 1229.738 | H20: =H18-H19 -> 1423.2233 | I20: =I18-I19 -> 1598.4367 | J20: =J18-J19 -> 1778.805
B21: CapEx (Cr) | C21: 765 | D21: 261 | E21: 120 | F21: =F16*F10 -> 140.42112 | G21: =G16*G10 -> 158.67587 | H21: =H16*H10 -> 173.70049 | I21: =I16*I10 -> 186.58794 | J21: =J16*J10 -> 191.56362
B22: Net Working Capital (Cr) | C22: =C16*C11 -> 850.23 | D22: =D16*D11 -> 909.324 | E22: =E16*E11 -> 1171.482 | F22: =F16*F11 -> 1316.448 | G22: =G16*G11 -> 1462.7931 | H22: =H16*H11 -> 1624.94 | I22: =I16*I11 -> 1772.5854 | J22: =J16*J11 -> 1915.6362
B23: Δ Net Working Capital (Cr) — (increase=cash outflow) | D23: =D22-C22 -> 59.094 | E23: =E22-D22 -> 262.158 | F23: =F22-E22 -> 144.966 | G23: =G22-F22 -> 146.34514 | H23: =H22-G22 -> 162.1469 | I23: =I22-H22 -> 147.64541 | J23: =J22-I22 -> 143.05076
B24: Interest Expense (Cr) | C24: 36 | D24: 44 | E24: 12 | F24: =F12 -> 8 | G24: =G12 -> 6 | H24: =H12 -> 5 | I24: =I12 -> 5 | J24: =J12 -> 5
B25: Tax Rate % | C25: =C13 -> 0.258 | D25: =D13 -> 0.261 | E25: =E13 -> 0.259 | F25: =F13 -> 0.258 | G25: =G13 -> 0.258 | H25: =H13 -> 0.258 | I25: =I13 -> 0.258 | J25: =J13 -> 0.258
A27: # | B27: TORRENT PHARMACEUTICALS — KEY DRIVERS (INPUTS ONLY)
B28: Revenue Growth % (YoY) | C28: - | D28: 0.1151 | E28: 0.0735 | F28: 0.132 | G28: 0.12 | H28: 0.12 | I28: 0.11 | J28: 0.085
B29: EBITDA Margin % | C29: 0.296 | D29: 0.314 | E29: 0.323 | F29: 0.329 | G29: 0.333 | H29: 0.335 | I29: 0.337 | J29: 0.338
B30: D&A as % of Revenue | C30: 0.0735 | D30: 0.0753 | E30: 0.069 | F30: 0.068 | G30: 0.067 | H30: 0.066 | I30: 0.065 | J30: 0.064
B31: Interest Expense (Cr) — Torrent standalone (post deal) | C31: 333 | D31: 354 | E31: 252 | F31: 1050 | G31: 980 | H31: 850 | I31: 650 | J31: 450
B32: Effective Tax Rate % | C32: 0.328 | D32: 0.298 | E32: 0.285 | F32: 0.27 | G32: 0.27 | H32: 0.27 | I32: 0.27 | J32: 0.27
B33: CapEx as % of Revenue | C33: 0.0597 | D33: 0.0404 | E33: 0.0531 | F33: 0.042 | G33: 0.041 | H33: 0.04 | I33: 0.036 | J33: 0.033
B35: TORRENT — DERIVED FINANCIALS (Formula-calculated from drivers above)
B36: Revenue (Cr) | C36: 9620 | D36: 10728 | E36: 11516 | F36: =E36*(1+F28) -> 13036.112 | G36: =F36*(1+G28) -> 14600.445 | H36: =G36*(1+H28) -> 16352.499 | I36: =H36*(1+I28) -> 18151.274 | J36: =I36*(1+J28) -> 19694.132
B37: EBITDA (Cr) | C37: 2842 | D37: 3368 | E37: 3721 | F37: =F36*F29 -> 4288.8808 | G37: =G36*G29 -> 4861.9483 | H37: =H36*H29 -> 5478.0871 | I37: =I36*I29 -> 6116.9793 | J37: =J36*J29 -> 6656.6166
B38: D&A (Cr) | C38: 707 | D38: 808 | E38: 795 | F38: =F36*F30 -> 886.45562 | G38: =G36*G30 -> 978.22984 | H38: =H36*H30 -> 1079.2649 | I38: =I36*I30 -> 1179.8328 | J38: =J36*J30 -> 1260.4245
B39: EBIT (Cr) | C39: =C37-C38 -> 2135 | D39: =D37-D38 -> 2560 | E39: =E37-E38 -> 2926 | F39: =F37-F38 -> 3402.4252 | G39: =G37-G38 -> 3883.7185 | H39: =H37-H38 -> 4398.8222 | I39: =I37-I38 -> 4937.1465 | J39: =J37-J38 -> 5396.1922
B40: Interest Expense (Cr) | C40: 333 | D40: 354 | E40: 252 | F40: =F31 -> 1050 | G40: =G31 -> 980 | H40: =H31 -> 850 | I40: =I31 -> 650 | J40: =J31 -> 450
B41: Tax Rate % | C41: =C32 -> 0.328 | D41: =D32 -> 0.298 | E41: =E32 -> 0.285 | F41: =F32 -> 0.27 | G41: =G32 -> 0.27 | H41: =H32 -> 0.27 | I41: =I32 -> 0.27 | J41: =J32 -> 0.27
B42: CapEx (Cr) | C42: 574 | D42: 433 | E42: 612 | F42: =F36*F33 -> 547.5167 | G42: =G36*G33 -> 598.61826 | H42: =H36*H33 -> 654.09996 | I42: =I36*I33 -> 653.44586 | J42: =J36*J33 -> 649.90636
B43: PAT (Cr) — Torrent Standalone | C43: 1245 | D43: 1656 | E43: 1911 | F43: =(F39-F40)*( 1-F41) -> 1717.2704 | G43: =(G39-G40)*( 1-G41) -> 2119.7145 | H43: =(H39-H40)*( 1-H41) -> 2590.6402 | I43: =(I39-I40)*( 1-I41) -> 3129.6169 | J43: =(J39-J40)*( 1-J41) -> 3610.7203
B44: Shares Outstanding — Torrent pre-merger (Cr) | C44: 33.84 | D44: =C44 -> 33.84 | E44: =C44 -> 33.84 | F44: =C44 -> 33.84 | G44: =C44 -> 33.84 | H44: =C44 -> 33.84 | I44: =C44 -> 33.84 | J44: =C44 -> 33.84
A46: # | B46: DEAL PARAMETERS & FINANCING ASSUMPTIONS
B47: JB Fully Diluted Shares (Crores) | C47: 16.05
B48: SPA Price per Share — KKR | C48: 1600
B49: Open Offer Price per Share | C49: 1639.18
B50: KKR Stake Acquired % | C50: 0.4639
B51: ESOP Stake Acquired % | C51: 0.0241
B52: Open Offer % Accepted (assumption) | C52: 0.015
B53: NCD Bond Issuance (Cr) | C53: 12500
B54: NCD Blended Interest Rate % | C54: 0.076
B55: Interest (Amt) | C55: =C53*C54 -> 950
B56: Merger Swap: Torrent shares per 100 JB shares | C56: 51
B57: Torrent Share Price for Swap | C57: 3200
B58: JB Book Equity FY25 (Cr) | C58: 3434
B59: Fair Value Uplift on Brands & Intangibles (Cr) | C59: 2500
B60: Transaction Cost | C60: 0.005
B61: Goodwill/Intangibles Amortisation Policy (Years) | C61: 15
B62: Torrent Own Cash Used for Acquisition (Cr) | C62: =(('Deal Mechanics'!C8+'Deal Mechanics'!C10+'Deal Mechanics'!C13+('Deal Mechanics'!C15*Assumptions!C60))-(Assumptions!C53+'Deal Mechanics'!C16)) -> 362.10495
B63: Goodwill Amortisation p.a. (Cr) — derived | C63: =((C47*C48)-C58-C59)/C61 -> 1316.4

Sheet Standalone Torrent
B1: TORRENT PHARMACEUTICALS — STANDALONE 3 STATEMENT MODEL
B2: All values derived from Assumptions sheet drivers | ₹ Crores
B4: INCOME STATEMENT
C5: FY23A | D5: FY24A | E5: FY25A | F5: FY26E | G5: FY27E | H5: FY28E | I5: FY29E | J5: FY30E
B6: Revenue | C6: =Assumptions!C36 -> 9620 | D6: =Assumptions!D36 -> 10728 | E6: =Assumptions!E36 -> 11516 | F6: =Assumptions!F36 -> 13036.112 | G6: =Assumptions!G36 -> 14600.445 | H6: =Assumptions!H36 -> 16352.499 | I6: =Assumptions!I36 -> 18151.274 | J6: =Assumptions!J36 -> 19694.132
B7: Revenue Growth YoY % | C7: - | D7: =Assumptions!D28 -> 0.1151 | E7: =Assumptions!E28 -> 0.0735 | F7: =Assumptions!F28 -> 0.132 | G7: =Assumptions!G28 -> 0.12 | H7: =Assumptions!H28 -> 0.12 | I7: =Assumptions!I28 -> 0.11 | J7: =Assumptions!J28 -> 0.085
B8: EBITDA | C8: =Assumptions!C37 -> 2842 | D8: =Assumptions!D37 -> 3368 | E8: =Assumptions!E37 -> 3721 | F8: =Assumptions!F37 -> 4288.8808 | G8: =Assumptions!G37 -> 4861.9483 | H8: =Assumptions!H37 -> 5478.0871 | I8: =Assumptions!I37 -> 6116.9793 | J8: =Assumptions!J37 -> 6656.6166
B9: EBITDA Margin % | C9: =Assumptions!C29 -> 0.296 | D9: =Assumptions!D29 -> 0.314 | E9: =Assumptions!E29 -> 0.323 | F9: =Assumptions!F29 -> 0.329 | G9: =Assumptions!G29 -> 0.333 | H9: =Assumptions!H29 -> 0.335 | I9: =Assumptions!I29 -> 0.337 | J9: =Assumptions!J29 -> 0.338
B10: Depreciation & Amortisation | C10: =Assumptions!C38 -> 707 | D10: =Assumptions!D38 -> 808 | E10: =Assumptions!E38 -> 795 | F10: =Assumptions!F38 -> 886.45562 | G10: =Assumptions!G38 -> 978.22984 | H10: =Assumptions!H38 -> 1079.2649 | I10: =Assumptions!I38 -> 1179.8328 | J10: =Assumptions!J38 -> 1260.4245
B11: EBIT | C11: =Assumptions!C39 -> 2135 | D11: =Assumptions!D39 -> 2560 | E11: =Assumptions!E39 -> 2926 | F11: =Assumptions!F39 -> 3402.4252 | G11: =Assumptions!G39 -> 3883.7185 | H11: =Assumptions!H39 -> 4398.8222 | I11: =Assumptions!I39 -> 4937.1465 | J11: =Assumptions!J39 -> 5396.1922
B12: Interest Expense | C12: =Assumptions!C40 -> 333 | D12: =Assumptions!D40 -> 354 | E12: =Assumptions!E40 -> 252 | F12: =Assumptions!F40 -> 1050 | G12: =Assumptions!G40 -> 980 | H12: =Assumptions!H40 -> 850 | I12: =Assumptions!I40 -> 650 | J12: =Assumptions!J40 -> 450
B13: Other Income / (Expense) | C13: 45 | D13: 146 | E13: -1 | F13: 50 | G13: 60 | H13: 65 | I13: 70 | J13: 75
B14: PBT | C14: =C11-C12+C13 -> 1847 | D14: =D11-D12+D13 -> 2352 | E14: =E11-E12+E13 -> 2673 | F14: =F11-F12+F13 -> 2402.4252 | G14: =G11-G12+G13 -> 2963.7185 | H14: =H11-H12+H13 -> 3613.8222 | I14: =I11-I12+I13 -> 4357.1465 | J14: =J11-J12+J13 -> 5021.1922
B15: Tax | C15: =MAX(0,C14*Assumptions!C41) -> 605.816 | D15: =MAX(0,D14*Assumptions!D41) -> 700.896 | E15: =MAX(0,E14*Assumptions!E41) -> 761.805 | F15: =MAX(0,F14*Assumptions!F41) -> 648.65481 | G15: =MAX(0,G14*Assumptions!G41) -> 800.20399 | H15: =MAX(0,H14*Assumptions!H41) -> 975.73199 | I15: =MAX(0,I14*Assumptions!I41) -> 1176.4295 | J15: =MAX(0,J14*Assumptions!J41) -> 1355.7219
B16: PAT | C16: =C14-C15 -> 1241.184 | D16: =D14-D15 -> 1651.104 | E16: =E14-E15 -> 1911.195 | F16: =F14-F15 -> 1753.7704 | G16: =G14-G15 -> 2163.5145 | H16: =H14-H15 -> 2638.0902 | I16: =I14-I15 -> 3180.7169 | J16: =J14-J15 -> 3665.4703
B17: EPS — Standalone (₹/share) | C17: 36.79 | D17: 48.94 | E17: 56.47 | F17: =F16/Assumptions!$C$44 -> 51.825367 | G17: =G16/Assumptions!$C$44 -> 63.933643 | H17: =H16/Assumptions!$C$44 -> 77.957748 | I17: =I16/Assumptions!$C$44 -> 93.992817 | J17: =J16/Assumptions!$C$44 -> 108.31768

Sheet Standalone JBChem
B1: J.B. CHEMICALS & PHARMACEUTICALS — STANDALONE 3-STATEMENT MODEL
B2: All values derived from Assumptions sheet drivers | ₹ Crores | FY ending March 31
B4: INCOME STATEMENT
C5: FY23A | D5: FY24A | E5: FY25A | F5: FY26E | G5: FY27E | H5: FY28E | I5: FY29E | J5: FY30E
B6: Revenue | C6: =Assumptions!C16 -> 3149 | D6: =Assumptions!D16 -> 3484 | E6: =Assumptions!E16 -> 3918 | F6: =Assumptions!F16 -> 4388.16 | G6: =Assumptions!G16 -> 4958.6208 | H6: =Assumptions!H16 -> 5603.2415 | I6: =Assumptions!I16 -> 6219.5981 | J6: =Assumptions!J16 -> 6841.5579
B7: Revenue Growth YoY % | C7: - | D7: =D6/C6-1 -> 0.10638298 | E7: =E6/D6-1 -> 0.12456946 | F7: =F6/E6-1 -> 0.12 | G7: =G6/F6-1 -> 0.13 | H7: =H6/G6-1 -> 0.13 | I7: =I6/H6-1 -> 0.11 | J7: =J6/I6-1 -> 0.1
B8: Gross Profit | C8: =Assumptions!C17 -> 1978 | D8: =Assumptions!D17 -> 2299 | E8: =Assumptions!E17 -> 2602 | F8: =Assumptions!F17 -> 2940.0672 | G8: =Assumptions!G17 -> 3347.069 | H8: =Assumptions!H17 -> 3810.2042 | I8: =Assumptions!I17 -> 4241.7659 | J8: =Assumptions!J17 -> 4679.6256
B9: Gross Margin % | C9: =C8/C6 -> 0.62813592 | D9: =D8/D6 -> 0.65987371 | E9: =E8/E6 -> 0.66411434 | F9: =F8/F6 -> 0.67 | G9: =G8/G6 -> 0.675 | H9: =H8/H6 -> 0.68 | I9: =I8/I6 -> 0.682 | J9: =J8/J6 -> 0.684
B10: EBITDA | C10: =Assumptions!C18 -> 696 | D10: =Assumptions!D18 -> 939 | E10: =Assumptions!E18 -> 1087 | F10: =Assumptions!F18 -> 1250.6256 | G10: =Assumptions!G18 -> 1438 | H10: =Assumptions!H18 -> 1652.9562 | I10: =Assumptions!I18 -> 1853.4402 | J10: =Assumptions!J18 -> 2052.4674
B11: EBITDA Margin % | C11: =C10/C6 -> 0.22102255 | D11: =D10/D6 -> 0.2695178 | E11: =E10/E6 -> 0.27743747 | F11: =F10/F6 -> 0.285 | G11: =G10/G6 -> 0.29 | H11: =H10/H6 -> 0.295 | I11: =I10/I6 -> 0.298 | J11: =J10/J6 -> 0.3
B12: Depreciation & Amortisation | C12: =Assumptions!C19 -> 114 | D12: =Assumptions!D19 -> 138 | E12: =Assumptions!E19 -> 171 | F12: =Assumptions!F19 -> 188.69088 | G12: =Assumptions!G19 -> 208.26207 | H12: =Assumptions!H19 -> 229.7329 | I12: =Assumptions!I19 -> 255.00352 | J12: =Assumptions!J19 -> 273.66232
B13: EBIT | C13: =Assumptions!C20 -> 582 | D13: =Assumptions!D20 -> 801 | E13: =Assumptions!E20 -> 916 | F13: =Assumptions!F20 -> 1061.9347 | G13: =Assumptions!G20 -> 1229.738 | H13: =Assumptions!H20 -> 1423.2233 | I13: =Assumptions!I20 -> 1598.4367 | J13: =Assumptions!J20 -> 1778.805
B14: Interest Expense | C14: =Assumptions!C24 -> 36 | D14: =Assumptions!D24 -> 44 | E14: =Assumptions!E24 -> 12 | F14: =Assumptions!F24 -> 8 | G14: =Assumptions!G24 -> 6 | H14: =Assumptions!H24 -> 5 | I14: =Assumptions!I24 -> 5 | J14: =Assumptions!J24 -> 5
B15: Other Income | C15: 10 | D15: 37 | E15: 38 | F15: 20 | G15: 20 | H15: 20 | I15: 20 | J15: 20
B16: PBT | C16: =C13-C14+C15 -> 556 | D16: =D13-D14+D15 -> 794 | E16: =E13-E14+E15 -> 942 | F16: =F13-F14+F15 -> 1073.9347 | G16: =G13-G14+G15 -> 1243.738 | H16: =H13-H14+H15 -> 1438.2233 | I16: =I13-I14+I15 -> 1613.4367 | J16: =J13-J14+J15 -> 1793.805
B17: Tax | C17: =MAX(0,C16*Assumptions!C25) -> 143.448 | D17: =MAX(0,D16*Assumptions!D25) -> 207.234 | E17: =MAX(0,E16*Assumptions!E25) -> 243.978 | F17: =MAX(0,F16*Assumptions!F25) -> 277.07516 | G17: =MAX(0,G16*Assumptions!G25) -> 320.88439 | H17: =MAX(0,H16*Assumptions!H25) -> 371.06162 | I17: =MAX(0,I16*Assumptions!I25) -> 416.26667 | J17: =MAX(0,J16*Assumptions!J25) -> 462.8017
B18: PAT | C18: =C16-C17 -> 412.552 | D18: =D16-D17 -> 586.766 | E18: =E16-E17 -> 698.022 | F18: =F16-F17 -> 796.85956 | G18: =G16-G17 -> 922.85357 | H18: =H16-H17 -> 1067.1617 | I18: =I16-I17 -> 1197.17 | J18: =J16-J17 -> 1331.0033
B19: PAT Margin % | C19: =C18/C6 -> 0.13101048 | D19: =D18/D6 -> 0.16841734 | E19: =E18/E6 -> 0.17815773 | F19: =F18/F6 -> 0.1815931 | G19: =G18/G6 -> 0.18611094 | H19: =H18/H6 -> 0.19045435 | I19: =I18/I6 -> 0.1924835 | J19: =J18/J6 -> 0.19454682
B20: EPS (₹/share) | C20: 26.48 | D20: 35.61 | E20: 42.37 | F20: =F18/Assumptions!$C$47 -> 49.648571 | G20: =G18/Assumptions!$C$47 -> 57.498664 | H20: =H18/Assumptions!$C$47 -> 66.489827 | I20: =I18/Assumptions!$C$47 -> 74.590033 | J20: =J18/Assumptions!$C$47 -> 82.928557
B22: FREE CASH FLOW (UFCF) FOR DCF
C23: FY23A | D23: FY24A | E23: FY25A | F23: FY26E | G23: FY27E | H23: FY28E | I23: FY29E | J23: FY30E
B24: EBITDA | C24: =C10 -> 696 | D24: =D10 -> 939 | E24: =E10 -> 1087 | F24: =F10 -> 1250.6256 | G24: =G10 -> 1438 | H24: =H10 -> 1652.9562 | I24: =I10 -> 1853.4402 | J24: =J10 -> 2052.4674
B25: (-) Cash Tax on EBIT | C25: =-Assumptions!C20*Assumptions!C25 -> -150.156 | D25: =-Assumptions!D20*Assumptions!D25 -> -209.061 | E25: =-Assumptions!E20*Assumptions!E25 -> -237.244 | F25: =-Assumptions!F20*Assumptions!F25 -> -273.97916 | G25: =-Assumptions!G20*Assumptions!G25 -> -317.27239 | H25: =-Assumptions!H20*Assumptions!H25 -> -367.19162 | I25: =-Assumptions!I20*Assumptions!I25 -> -412.39667 | J25: =-Assumptions!J20*Assumptions!J25 -> -458.9317
B26: (-) CapEx | C26: =-Assumptions!C21 -> -765 | D26: =-Assumptions!D21 -> -261 | E26: =-Assumptions!E21 -> -120 | F26: =-Assumptions!F21 -> -140.42112 | G26: =-Assumptions!G21 -> -158.67587 | H26: =-Assumptions!H21 -> -173.70049 | I26: =-Assumptions!I21 -> -186.58794 | J26: =-Assumptions!J21 -> -191.56362
B27: (-) Increase in Net Working Capital | C27: -94 | D27: -30 | E27: 7 | F27: =-Assumptions!F23 -> -144.966 | G27: =-Assumptions!G23 -> -146.34514 | H27: =-Assumptions!H23 -> -162.1469 | I27: =-Assumptions!I23 -> -147.64541 | J27: =-Assumptions!J23 -> -143.05076
B28: UNLEVERED FREE CASH FLOW (UFCF) | C28: =C24+C25+C26+C27 -> -313.156 | D28: =D24+D25+D26+D27 -> 438.939 | E28: =E24+E25+E26+E27 -> 736.756 | F28: =F24+F25+F26+F27 -> 691.25932 | G28: =G24+G25+G26+G27 -> 815.70664 | H28: =H24+H25+H26+H27 -> 949.91723 | I28: =I24+I25+I26+I27 -> 1106.8102 | J28: =J24+J25+J26+J27 -> 1258.9213

Sheet Synergies
B1: SYNERGY MODEL — COST & REVENUE SYNERGIES
B2: Source: Torrent Q3FY26 CC — Aman Mehta: ₹400-450Cr cost synergies over 3 years
A4: # | B4: COST SYNERGIES (₹ Crores)
C5: FY27E (Yr1) | D5: FY28E (Yr2) | E5: FY29E (Yr3) | F5: FY30E (Yr4) | G5: FY31E (Yr5)
B6: 1. Field Force & MR Rationalisation | C6: 45 | D6: 80 | E6: 100 | F6: 110 | G6: 115
B7: 2. Procurement & API Sourcing | C7: 20 | D7: 40 | E7: 55 | F7: 60 | G7: 65
B8: 3. Manufacturing & Plant Utilisation | C8: 10 | D8: 25 | E8: 40 | F8: 50 | G8: 55
B9: 4. Corporate Overheads & IT | C9: 10 | D9: 15 | E9: 20 | F9: 22 | G9: 25
B10: 5. Trade Generics Discontinuation | C10: 0 | D10: 0 | E10: 30 | F10: 35 | G10: 38
B11: TOTAL COST SYNERGIES | C11: =SUM(C6:C10) -> 85 | D11: =SUM(D6:D10) -> 160 | E11: =SUM(E6:E10) -> 245 | F11: =SUM(F6:F10) -> 277 | G11: =SUM(G6:G10) -> 298
A13: # | B13: REVENUE SYNERGIES (₹ Crores)
C14: FY27E (Yr1) | D14: FY28E (Yr2) | E14: FY29E (Yr3) | F14: FY30E (Yr4) | G14: FY31E (Yr5)
B15: 1. Cardiac/Gastro Cross-Selling (India) | C15: 0 | D15: 30 | E15: 60 | F15: 75 | G15: 85
B16: 2. International EM Scale (Russia/Africa) | C16: 0 | D16: 15 | E16: 30 | F16: 40 | G16: 45
B17: 3. Ophthalmology & Novartis Portfolio | C17: 0 | D17: 20 | E17: 45 | F17: 60 | G17: 70
B18: 4. CDMO Lozenges Utilisation | C18: 0 | D18: 10 | E18: 20 | F18: 30 | G18: 35
B19: TOTAL REVENUE SYNERGIES | C19: =SUM(C15:C18) -> 0 | D19: =SUM(D15:D18) -> 75 | E19: =SUM(E15:E18) -> 155 | F19: =SUM(F15:F18) -> 205 | G19: =SUM(G15:G18) -> 235
A21: # | B21: ONE TIME INTEGRATION COSTS (₹ Crores) — EXPENSED AGAINST SYNERGIES
C22: FY27E (Yr1) | D22: FY28E (Yr2) | E22: FY29E (Yr3) | F22: FY30E (Yr4) | G22: FY31E (Yr5)
B23: Redundancy & Voluntary Retirement (Cr) | C23: 80 | D23: 60 | E23: 20 | F23: 0 | G23: 0
B24: IT Systems Integration (Cr) | C24: 30 | D24: 20 | E24: 0 | F24: 0 | G24: 0
B25: Plant & Process Harmonisation (Cr) | C25: 40 | D25: 0 | E25: 0 | F25: 0 | G25: 0
B26: TOTAL INTEGRATION COSTS | C26: =SUM(C23:C25) -> 150 | D26: =SUM(D23:D25) -> 80 | E26: =SUM(E23:E25) -> 20 | F26: =SUM(F23:F25) -> 0 | G26: =SUM(G23:G25) -> 0
A28: # | B28: NET SYNERGY BENEFIT (Cost Synergies + Revenue Synergies − Integration Costs)
C29: FY27E (Yr1) | D29: FY28E (Yr2) | E29: FY29E (Yr3) | F29: FY30E (Yr4) | G29: FY31E (Yr5)
B30: NET SYNERGY TO P&L (₹ Cr) | C30: =C11+C19-C26 -> -65 | D30: =D11+D19-D26 -> 155 | E30: =E11+E19-E26 -> 380 | F30: =F11+F19-F26 -> 482 | G30: =G11+G19-G26 -> 533
B32: SYNERGY VALUATION ANALYSIS (Cr)
B34: After Tax Syenergy | C34: =C30*(1-Assumptions!F32) -> -47.45 | D34: =D30*(1-Assumptions!G32) -> 113.15 | E34: =E30*(1-Assumptions!H32) -> 277.4 | F34: =F30*(1-Assumptions!I32) -> 351.86 | G34: =G30*(1-Assumptions!J32) -> 389.09
B35: Discount Factor | C35: 0.5 | D35: =C35+1 -> 1.5 | E35: =D35+1 -> 2.5 | F35: =E35+1 -> 3.5 | G35: =F35+1 -> 4.5
B36: Pv of Synergy | C36: =C34/(1+Valuation!$D$19)^Synergies!C35 -> -45.090818 | D36: =D34/(1+Valuation!$D$19)^Synergies!D35 -> 97.097991 | E36: =E34/(1+Valuation!$D$19)^Synergies!E35 -> 214.9641 | F36: =F34/(1+Valuation!$D$19)^Synergies!F35 -> 246.22558 | G36: =G34/(1+Valuation!$D$19)^Synergies!G35 -> 245.87656
B38: FY31 after-tax synergy | C38: =G34 -> 389.09
B39: Exit Multiple | C39: 18
B40: Terminal Synergy Value | C40: =G30*C39 -> 9594
B41: Discount Terminal Value | C41: =C40/(1+Valuation!$D$19)^5 -> 5761.2758
B42: Terminal Synergy Value | C42: =SUM(C36:G36)+C41 -> 6520.3492

Sheet Deal Mechanics
B1: DEAL MECHANICS — PURCHASE PRICE | SOURCES & USES | GOODWILL | SWAP
B2: All figures in ₹ Crores | Linked directly from Assumptions sheet
A4: # | B4: SECTION 1 — PURCHASE PRICE ANALYSIS
B5: JB Fully Diluted Shares (Crores) | C5: =Assumptions!$C$47 -> 16.05
B6: SPA Price per Share — KKR | C6: =Assumptions!$C$48 -> 1600
B7: KKR Stake Acquired (%) | C7: =Assumptions!$C$50 -> 0.4639
B8: (A) KKR SPA Consideration (Cr) | C8: =C5*C6*C7 -> 11912.952
B9: ESOP Stake Acquired (%) | C9: =Assumptions!$C$51 -> 0.0241
B10: (B) ESOP Stake Consideration (Cr) | C10: =C5*Assumptions!$C$51*Assumptions!$C$48 -> 618.888
B11: Open Offer Price per Share | C11: =Assumptions!$C$49 -> 1639.18
B12: Open Offer % Accepted | C12: =Assumptions!$C$52 -> 0.015
B13: (C) Open Offer Consideration (Cr) | C13: =C5*C12*C11 -> 394.63259
B15: TOTAL CASH CONSIDERATION (A+B+C) | C15: =C8+C10+C13 -> 12926.473
B16: (-) JB Cash Acquired (net cash FY25) | C16: 129
B17: Total Debt | C17: 28
B18: (+) JB Net Debt at Acquisition | C18: =C17-C16 -> -101
B19: NET PURCHASE PRICE (EQUITY VALUE, Cr) | C19: =C15-C16 -> 12797.473
B20: EV of Torrent's Acquired Stake (~50%, Cr) | C20: =C19+C18 -> 12696.473
B21: Implied EV/EBITDA — Acquired Stake Only (not deal metric) | C21: =C20/Assumptions!$C$18 -> 18.242058
B22: Headline Deal EV/EBITDA — 100% Implied Basis (deal metric) | C22: =(Assumptions!$C$47*Assumptions!$C$48+C17)/Assumptions!$E$18 -> 23.650414
B23: Headline Deal EV/EBITDA — FY26E Basis (mgmt cited) | C23: =(Assumptions!$C$47*Assumptions!$C$48+C17)/Assumptions!$F$18 -> 20.556112
A25: # | B25: SECTION 2 — SOURCES & USES OF FUNDS
B26: USES OF FUNDS | C26: ₹ Crores | D26: SOURCES OF FUNDS | E26: ₹ Crores
B27: (A) KKR SPA Payment | C27: =C8 -> 11912.952 | D27: NCD Bond Issuance (7.6% coupon) | E27: =Assumptions!$C$53 -> 12500
B28: (B) ESOP Payment | C28: =C10 -> 618.888 | D28: Torrent Internal Cash / Accruals | E28: =Assumptions!C62 -> 362.10495
B29: (C) Open Offer Payment | C29: =C13 -> 394.63259 | D29: JB Cash on Balance Sheet Acquired | E29: 129
B30: Transaction Costs (0.5% of cash) | C30: =C15*Assumptions!C60 -> 64.632363 | D30: — | E30: 0
B31: TOTAL USES | C31: =SUM(C27:C30) -> 12991.105 | D31: TOTAL SOURCES | E31: =E27+E28+E29+E30 -> 12991.105
B32: ⚡ BALANCE CHECK (Sources − Uses) MUST = 0 | C32: =E31-C31 -> 0
A34: # | B34: SECTION 3 — GOODWILL & PURCHASE PRICE ALLOCATION
B35: (A) Total Equity Purchase Price (Cr) | C35: =Assumptions!C47*Assumptions!C48 -> 25680
B36: (B) JB Book Equity at Acquisition (Cr) | C36: =Assumptions!$C$58 -> 3434
B37: (C) Fair Value Uplift — Brands & Intangibles (Cr) | C37: =Assumptions!$C$59 -> 2500
B38: (D) Fair Value of Net Assets (B + C) | C38: =C36+C37 -> 5934
B39: GOODWILL (A − D) | C39: =C35-C38 -> 19746
B40: Amortisation Policy (Years) | C40: =Assumptions!$C$61 -> 15
B41: Annual P&L Amortisation Charge (Cr) | C41: =C39/C40 -> 1316.4
A44: # | B44: SECTION 4 — MERGER SHARE ISSUANCE (51:100 SWAP RATIO)
B45: Torrent Pre-Merger Shares Outstanding (Cr) | C45: =Assumptions!$C$44 -> 33.84
B46: JB Fully Diluted Shares (Cr) | C46: =Assumptions!$C$47 -> 16.05
B47: Torrent Stake in JB post-deals (%) | C47: =Assumptions!$C$50+Assumptions!$C$51+Assumptions!$C$52 -> 0.503
B48: JB Minority Shares (held by others, Cr) | C48: =Assumptions!$C$47*(1-C47) -> 7.97685
B49: Swap Ratio (Torrent per 100 JB shares) | C49: =Assumptions!$C$56 -> 51
B50: NEW Torrent Shares Issued in Merger (Cr) | C50: =C48*C49/100 -> 4.0681935
B51: TORRENT POST-MERGER SHARES TOTAL (Cr) | C51: =C45+C50 -> 37.908194
B52: Torrent Share Price at Swap | C52: =Assumptions!$C$57 -> 3200
B53: Share Consideration Value (Cr) | C53: =C50*C52 -> 13018.219
B55: TOTAL DEAL CONSIDERATION (Cash + Share Swap) | C55: =C15+C53 -> 25944.692

Sheet ProForma Combined
B1: PRO FORMA COMBINED — INCOME STATEMENT & BALANCE SHEET
B2: Torrent + JB Chemicals | FY26-30E | All ₹ Crores | Synergies phased per Synergies sheet
A4: # | B4: COMBINED INCOME STATEMENT
C5: FY26E | D5: FY27E | E5: FY28E | F5: FY29E | G5: FY30E | H5: 5yr CAGR
B6: Torrent Revenue (Cr) | C6: =Assumptions!F36 -> 13036.112 | D6: =Assumptions!G36 -> 14600.445 | E6: =Assumptions!H36 -> 16352.499 | F6: =Assumptions!I36 -> 18151.274 | G6: =Assumptions!J36 -> 19694.132
B7: JB Chemicals Revenue (Cr) | C7: =Assumptions!F16 -> 4388.16 | D7: =Assumptions!G16 -> 4958.6208 | E7: =Assumptions!H16 -> 5603.2415 | F7: =Assumptions!I16 -> 6219.5981 | G7: =Assumptions!J16 -> 6841.5579
B8: (+) Revenue Synergies (Cr) | C8: 0 | D8: =Synergies!C19 -> 0 | E8: =Synergies!D19 -> 75 | F8: =Synergies!E19 -> 155 | G8: =Synergies!F19 -> 205
B9: COMBINED REVENUE (Cr) | C9: =C6+C7+C8 -> 17424.272 | D9: =D6+D7+D8 -> 19559.066 | E9: =E6+E7+E8 -> 22030.74 | F9: =F6+F7+F8 -> 24525.872 | G9: =G6+G7+G8 -> 26740.69 | H9: =_xlfn.RRI(4,C9,G9) -> 0.1130239
B10: Revenue Growth YoY % | C10: - | D10: =D9/C9-1 -> 0.12251842 | E10: =E9/D9-1 -> 0.12636974 | F10: =F9/E9-1 -> 0.11325681 | G10: =G9/F9-1 -> 0.090305376
B12: Torrent EBITDA (Cr) | C12: =Assumptions!F37 -> 4288.8808 | D12: =Assumptions!G37 -> 4861.9483 | E12: =Assumptions!H37 -> 5478.0871 | F12: =Assumptions!I37 -> 6116.9793 | G12: =Assumptions!J37 -> 6656.6166
B13: JB EBITDA (Cr) | C13: =Assumptions!F18 -> 1250.6256 | D13: =Assumptions!G18 -> 1438 | E13: =Assumptions!H18 -> 1652.9562 | F13: =Assumptions!I18 -> 1853.4402 | G13: =Assumptions!J18 -> 2052.4674
B14: (+) Cost Synergies (Cr) | C14: 0 | D14: =Synergies!C11 -> 85 | E14: =Synergies!D11 -> 160 | F14: =Synergies!E11 -> 245 | G14: =Synergies!F11 -> 277
B15: (-) Integration Costs (Cr) | C15: 0 | D15: =-Synergies!C26 -> -150 | E15: =-Synergies!D26 -> -80 | F15: =-Synergies!E26 -> -20 | G15: =-Synergies!F26 -> 0
B16: COMBINED EBITDA (Cr) | C16: =C12+C13+C14+C15 -> 5539.5064 | D16: =D12+D13+D14+D15 -> 6234.9484 | E16: =E12+E13+E14+E15 -> 7211.0434 | F16: =F12+F13+F14+F15 -> 8195.4195 | G16: =G12+G13+G14+G15 -> 8986.084 | H16: =_xlfn.RRI(4,C16,G16) -> 0.12856051
B17: EBITDA Margin % | C17: =C16/C9 -> 0.31791896 | D17: =D16/D9 -> 0.31877536 | E17: =E16/E9 -> 0.32731734 | F17: =F16/F9 -> 0.33415405 | G17: =G16/G9 -> 0.33604533
B19: Combined D&A (ex-goodwill amort) | C19: =Assumptions!F38+Assumptions!F19 -> 1075.1465 | D19: =Assumptions!G38+Assumptions!G19 -> 1186.4919 | E19: =Assumptions!H38+Assumptions!H19 -> 1308.9978 | F19: =Assumptions!I38+Assumptions!I19 -> 1434.8363 | G19: =Assumptions!J38+Assumptions!J19 -> 1534.0868
B20: (-) Goodwill/Intangible Amortisation (Cr) | C20: ='Deal Mechanics'!$C$41 -> 1316.4 | D20: ='Deal Mechanics'!$C$41 -> 1316.4 | E20: ='Deal Mechanics'!$C$41 -> 1316.4 | F20: ='Deal Mechanics'!$C$41 -> 1316.4 | G20: ='Deal Mechanics'!$C$41 -> 1316.4
B21: Total D&A incl. Goodwill Amort | C21: =C19+C20 -> 2391.5465 | D21: =D19+D20 -> 2502.8919 | E21: =E19+E20 -> 2625.3978 | F21: =F19+F20 -> 2751.2363 | G21: =G19+G20 -> 2850.4868
B22: EBIT (Cr) | C22: =C16-C21 -> 3147.96 | D22: =D16-D21 -> 3732.0564 | E22: =E16-E21 -> 4585.6455 | F22: =F16-F21 -> 5444.1832 | G22: =G16-G21 -> 6135.5972
B23: (-) Interest on Acquisition Debt (Cr) | C23: =Assumptions!F31 -> 1050 | D23: =Assumptions!G31 -> 980 | E23: =Assumptions!H31 -> 850 | F23: =Assumptions!I31 -> 650 | G23: =Assumptions!J31 -> 450
B24: Other Income (Cr) | C24: ='Standalone Torrent'!F13 -> 50 | D24: ='Standalone Torrent'!G13 -> 60 | E24: ='Standalone Torrent'!H13 -> 65 | F24: ='Standalone Torrent'!I13 -> 70 | G24: ='Standalone Torrent'!J13 -> 75
B25: PBT (Cr) | C25: =C22-C23+C24 -> 2147.96 | D25: =D22-D23+D24 -> 2812.0564 | E25: =E22-E23+E24 -> 3800.6455 | F25: =F22-F23+F24 -> 4864.1832 | G25: =G22-G23+G24 -> 5760.5972
B26: Tax @ 27% | C26: =MAX(0,C25*Assumptions!F32) -> 579.94919 | D26: =MAX(0,D25*Assumptions!G32) -> 759.25524 | E26: =MAX(0,E25*Assumptions!H32) -> 1026.1743 | F26: =MAX(0,F25*Assumptions!I32) -> 1313.3295 | G26: =MAX(0,G25*Assumptions!J32) -> 1555.3613
B27: COMBINED PAT (Cr) | C27: =C25-C26 -> 1568.0108 | D27: =D25-D26 -> 2052.8012 | E27: =E25-E26 -> 2774.4712 | F27: =F25-F26 -> 3550.8537 | G27: =G25-G26 -> 4205.236 | H27: =_xlfn.RRI(4,C27,G27) -> 0.27970637
B28: PAT Margin % | C28: =C27/C9 -> 0.08999003 | D28: =D27/D9 -> 0.10495395 | E28: =E27/E9 -> 0.12593636 | F28: =F27/F9 -> 0.14477992 | G28: =G27/G9 -> 0.15725982
A31: # | B31: PRO FORMA CAPITALIZATION & LEVERAGE (DAY 1 CLOSING)
B32: Metric
B33: Torrent Standalone Net Debt | C33: ='Summary FootballField'!H11 -> 2245.54
B34: JB Standalone Net Debt | C34: ='Summary FootballField'!I11 -> -143.39
B35: New Deal Debt Issued (NCDs) | C35: =Assumptions!C53 -> 12500
B36: Torrent Internal Cash Used for Deal | C36: ='Deal Mechanics'!E28 -> 362.10495
B37: Pro Forma Day 1 Net Debt | C37: =SUM(C33:C36) -> 14964.255
B38: Combined LTM EBITDA (FY25 Base) | C38: ='Summary FootballField'!J7 -> 4808
B39: Pro Forma Net Debt / EBITDA | C39: =C37/C38 -> 3.1123658

Sheet Accretion Dilution
B1: ACCRETION / DILUTION ANALYSIS
B2: Torrent Standalone EPS vs Combined EPS | Swap Ratio 51:100 | All values ₹
A4: # | B4: EPS BRIDGE — STANDALONE TO COMBINED
C5: FY26E | D5: FY27E | E5: FY28E | F5: FY29E | G5: FY30E
B6: Torrent Pre-Deal PAT — Excl. NCD Interest (Cr) | C6: ='Standalone Torrent'!F11*(1-Assumptions!F32) -> 2483.7704 | D6: ='Standalone Torrent'!G11*(1-Assumptions!G32) -> 2835.1145 | E6: ='Standalone Torrent'!H11*(1-Assumptions!H32) -> 3211.1402 | F6: ='Standalone Torrent'!I11*(1-Assumptions!I32) -> 3604.1169 | G6: ='Standalone Torrent'!J11*(1-Assumptions!J32) -> 3939.2203
B7: (+) JB Chemicals PAT (Cr) | C7: ='Standalone JBChem'!F18 -> 796.85956 | D7: ='Standalone JBChem'!G18 -> 922.85357 | E7: ='Standalone JBChem'!H18 -> 1067.1617 | F7: ='Standalone JBChem'!I18 -> 1197.17 | G7: ='Standalone JBChem'!J18 -> 1331.0033
B8: (+) Cost Synergies — After Tax (Cr) | C8: 0 | D8: =Synergies!C11*(1-Assumptions!G32) -> 62.05 | E8: =Synergies!D11*(1-Assumptions!H32) -> 116.8 | F8: =Synergies!E11*(1-Assumptions!I32) -> 178.85 | G8: =Synergies!F11*(1-Assumptions!J32) -> 202.21
B9: (+) Revenue Synergies — After Tax (Cr) | C9: 0 | D9: =Synergies!C19*(1-Assumptions!G32) -> 0 | E9: =Synergies!D19*(1-Assumptions!H32) -> 54.75 | F9: =Synergies!E19*(1-Assumptions!I32) -> 113.15 | G9: =Synergies!F19*(1-Assumptions!J32) -> 149.65
B10: (-) Integration Costs — After Tax (Cr) | C10: 0 | D10: =-Synergies!C26*(1-Assumptions!G32) -> -109.5 | E10: =-Synergies!D26*(1-Assumptions!H32) -> -58.4 | F10: =-Synergies!E26*(1-Assumptions!I32) -> -14.6 | G10: =-Synergies!F26*(1-Assumptions!J32) -> 0
B11: (-) Incremental Interest on NCDs — After Tax (Cr) | C11: =-Assumptions!F31*(1-Assumptions!F32) -> -766.5 | D11: =-Assumptions!G31*(1-Assumptions!G32) -> -715.4 | E11: =-Assumptions!H31*(1-Assumptions!H32) -> -620.5 | F11: =-Assumptions!I31*(1-Assumptions!I32) -> -474.5 | G11: =-Assumptions!J31*(1-Assumptions!J32) -> -328.5
B12: (-) Goodwill Amortisation — After Tax (Cr) | C12: =-'Deal Mechanics'!$C$41*(1-Assumptions!F32) -> -960.972 | D12: =-'Deal Mechanics'!$C$41*(1-Assumptions!G32) -> -960.972 | E12: =-'Deal Mechanics'!$C$41*(1-Assumptions!H32) -> -960.972 | F12: =-'Deal Mechanics'!$C$41*(1-Assumptions!I32) -> -960.972 | G12: =-'Deal Mechanics'!$C$41*(1-Assumptions!J32) -> -960.972
B13: COMBINED PAT ATTRIBUTABLE (₹ Cr) | C13: =C6+C7+C8+C9+C10+C11+C12 -> 1553.158 | D13: =D6+D7+D8+D9+D10+D11+D12 -> 2034.1461 | E13: =E6+E7+E8+E9+E10+E11+E12 -> 2809.9799 | F13: =F6+F7+F8+F9+F10+F11+F12 -> 3643.215 | G13: =G6+G7+G8+G9+G10+G11+G12 -> 4332.6116
B15: Torrent Pre-Merger Shares (Cr) | C15: =Assumptions!$C$44 -> 33.84 | D15: =Assumptions!$C$44 -> 33.84 | E15: =Assumptions!$C$44 -> 33.84 | F15: =Assumptions!$C$44 -> 33.84 | G15: =Assumptions!$C$44 -> 33.84
B16: (+) New Shares Issued in Merger (Cr) | C16: ='Deal Mechanics'!$C$50 -> 4.0681935 | D16: ='Deal Mechanics'!$C$50 -> 4.0681935 | E16: ='Deal Mechanics'!$C$50 -> 4.0681935 | F16: ='Deal Mechanics'!$C$50 -> 4.0681935 | G16: ='Deal Mechanics'!$C$50 -> 4.0681935
B17: COMBINED SHARES OUTSTANDING (Cr) | C17: =C15+C16 -> 37.908194 | D17: =D15+D16 -> 37.908194 | E17: =E15+E16 -> 37.908194 | F17: =F15+F16 -> 37.908194 | G17: =G15+G16 -> 37.908194
B19: Torrent Standalone EPS — Post-Deal Basis (₹) | C19: =Assumptions!F43/Assumptions!F44 -> 50.746762 | D19: =Assumptions!G43/Assumptions!G44 -> 62.639317 | E19: =Assumptions!H43/Assumptions!H44 -> 76.555562 | F19: =Assumptions!I43/Assumptions!I44 -> 92.48277 | G19: =Assumptions!J43/Assumptions!J44 -> 106.69977
B20: COMBINED ENTITY EPS (₹) | C20: =C13/C17 -> 40.971564 | D20: =D13/D17 -> 53.659799 | E20: =E13/E17 -> 74.125926 | F20: =F13/F17 -> 96.106267 | G20: =G13/G17 -> 114.29222
B22: ACCRETION / (DILUTION) — ₹ | C22: =C20-C19 -> -9.7751977 | D22: =D20-D19 -> -8.9795178 | E22: =E20-E19 -> -2.4296362 | F22: =F20-F19 -> 3.6234972 | G22: =G20-G19 -> 7.592449
B23: ACCRETION / (DILUTION) — % | C23: =C22/C19 -> -0.19262702 | D23: =D22/D19 -> -0.14335274 | E23: =E22/E19 -> -0.0317369 | F23: =F22/F19 -> 0.039180241 | G23: =G22/G19 -> 0.071157125

Sheet Valuation
B1: VALUATION — J.B. CHEMICALS & PHARMACEUTICALS
B2: Three Independent Methods: (1) DCF Intrinsic | (2) Comparable Companies | (3) Precedent Transactions | All ₹ Crores
A4: # | B4: METHOD 1: DCF — WACC
B6: Parameter | C6: Value
B7: Risk-Free Rate (10yr G-Sec) | C7: 0.068
B8: Equity Risk Premium - India | C8: 0.055
B9: Unlevered Beta (pharma peers avg) | C9: 0.72
B10: D/E Ratio (JB - near debt free) | C10: 0.01
B11: Tax Rate | C11: 0.258
B12: Relevered Beta | C12: =C9*(1+(1-C11)*C10) -> 0.7253424
B13: cost of Equiy (pre-tax) | C13: =C7+C12*C8 -> 0.10789383
B14: Cost of Debt (pre-tax) | C14: 0.076
B15: After-Tax Cost of Debt | C15: =C14*(1-C11) -> 0.056392
B16: Equity Weight | C16: 0.99
B17: Debt Weight | C17: 0.01
B18: Long Term Growth (g) | C18: 0.05
B19: WACC | C19: =(C13*C16)+(C15*C17) -> 0.10737881 | D19: =J48 -> 0.10737881
B21: UFCF PROJECTIONS & TERMINAL VALUE | C21: FY26E | D21: FY27E | E21: FY28E | F21: FY29E | G21: FY30E
B22: EBITDA (Cr) | C22: =Assumptions!F18 -> 1250.6256 | D22: =Assumptions!G18 -> 1438 | E22: =Assumptions!H18 -> 1652.9562 | F22: =Assumptions!I18 -> 1853.4402 | G22: =Assumptions!J18 -> 2052.4674
B23: (-) Cash Tax on EBIT | C23: =-Assumptions!F20*Assumptions!F13 -> -273.97916 | D23: =-Assumptions!G20*Assumptions!G13 -> -317.27239 | E23: =-Assumptions!H20*Assumptions!H13 -> -367.19162 | F23: =-Assumptions!I20*Assumptions!I13 -> -412.39667 | G23: =-Assumptions!J20*Assumptions!J13 -> -458.9317
B24: (-) CapEx | C24: =-Assumptions!F21 -> -140.42112 | D24: =-Assumptions!G21 -> -158.67587 | E24: =-Assumptions!H21 -> -173.70049 | F24: =-Assumptions!I21 -> -186.58794 | G24: =-Assumptions!J21 -> -191.56362
B25: (-) Δ Net Working Capital | C25: =-Assumptions!F23 -> -144.966 | D25: =-Assumptions!G23 -> -146.34514 | E25: =-Assumptions!H23 -> -162.1469 | F25: =-Assumptions!I23 -> -147.64541 | G25: =-Assumptions!J23 -> -143.05076
B26: UNLEVERED FREE CASH FLOW (UFCF) | C26: =C22+C23+C24+C25 -> 691.25932 | D26: =D22+D23+D24+D25 -> 815.70664 | E26: =E22+E23+E24+E25 -> 949.91723 | F26: =F22+F23+F24+F25 -> 1106.8102 | G26: =G22+G23+G24+G25 -> 1258.9213
B27: Discount Period (mid year) | C27: 0.5 | D27: =C27+1 -> 1.5 | E27: =D27+1 -> 2.5 | F27: =E27+1 -> 3.5 | G27: =F27+1 -> 4.5
B28: Discount Factor | C28: =1/(1+$D$19)^C27 -> 0.95028067 | D28: =1/(1+$D$19)^D27 -> 0.85813514 | E28: =1/(1+$D$19)^E27 -> 0.77492465 | F28: =1/(1+$D$19)^F27 -> 0.6997828 | G28: =1/(1+$D$19)^G27 -> 0.63192721
B29: PV of UFCF | C29: =C26*C28 -> 656.89037 | D29: =D26*D28 -> 699.98653 | E29: =E26*E28 -> 736.11428 | F29: =F26*F28 -> 774.52674 | G29: =G26*G28 -> 795.54661
A31: # | B31: TERMINAL VALUE (EV/EBITDA Exit Multiple) | C31: Value
B32: Terminal EBITDA (FY31E) | C32: =G22*(1+C18) -> 2155.0907
B33: Exit Multiple | C33: =J49 -> 18
B34: Terminal Enterprise Value | C34: =C32*C33 -> 38791.633
B35: PV of Terminal Enterprise Value | C35: =C34/(1+D19)^5 -> 23294.694
B36: Sum of PV of FCFF | C36: =SUM(C29:G29) -> 3663.0645
B38: DCF SUMMARY
B39: ENTERPRISE VALUE — DCF | C39: =C36+C35 -> 26957.759
B40: (-) Net Debt | C40: ='Summary FootballField'!I11 -> -143.39
B41: EQUITY VALUE — DCF | C41: =C39-C40 -> 27101.149
B42: Implied Price/Share (₹) | C42: =C41/Assumptions!C47 -> 1688.5451
B43: Deal Price | C43: ='Deal Mechanics'!C6 -> 1600
B44: Premium/(Discount) of Deal to DCF | C44: =C43/C42-1 -> -0.052438687
A46: # | B46: DCF SENSITIVITY ANALYSIS
B47: WACC ↓ | C47: EXIT MULTIPLE ➔
B48: =$C$42 -> 1688.5451 | C48: 16 | D48: 17 | E48: 18 | F48: 19 | G48: 20 | J48: 0.10737881
B49: 0.097 | C49: 1595.1443 | D49: 1679.6639 | E49: 1764.1835 | F49: 1848.703 | G49: 1933.2226 | J49: 18
B50: 0.102 | C50: 1561.9829 | D50: 1644.6024 | E50: 1727.2219 | F50: 1809.8414 | G50: 1892.4609
B51: 0.10737881 | C51: 1527.2803 | D51: 1607.9127 | E51: 1688.5451 | F51: 1769.1775 | G51: 1849.8098
B52: 0.115 | C52: 1479.771 | D52: 1557.6851 | E52: 1635.5992 | F52: 1713.5133 | G52: 1791.4275
B53: 0.12 | C53: 1449.6204 | D53: 1525.8109 | E53: 1602.0013 | F53: 1678.1917 | G53: 1754.3822
A56: # | B56: METHOD 2: COMPARABLE COMPANY ANALYSIS
B58: Company | C58: Market Cap (Cr) | D58: Enterprise Value (Cr) | E58: LTM EBITDA (Cr) | F58: EV / EBITDA | G58: P / E Ratio
B59: Alkem | C59: 65748 | D59: 66556 | E59: 2835 | F59: =D59/E59 -> 23.476543 | G59: 27.4
B60: Ajanta Pharma | C60: 39367 | D60: 39522 | E60: 1365 | F60: =D60/E60 -> 28.953846 | G60: 37.3
B61: Eris Lifesciences | C61: 19247 | D61: 21538 | E61: 1120 | F61: =D61/E61 -> 19.230357 | G61: 30.4
B62: Mankind | C62: 103504 | D62: 109333 | E62: 3629 | F62: =D62/E62 -> 30.127583 | G62: 51.6
B63: Ipca | C63: 42039 | D63: 43054 | E63: 1812 | F63: =D63/E63 -> 23.760486 | G63: 39.8
B65: J.B. Chemicals (Subject) | C65: 34966 | D65: 34823 | E65: 1195 | F65: =D65/E65 -> 29.140586 | G65: 47.9
B66: MEDIAN (ex-JB) | C66: =MEDIAN(C59:C63) -> 42039 | D66: =MEDIAN(D59:D63) -> 43054 | E66: =MEDIAN(E59:E63) -> 1812 | F66: =MEDIAN(F59:F63) -> 23.760486 | G66: =MEDIAN(G59:G63) -> 37.3
B67: MEAN (ex-JB) | C67: =AVERAGE(C59:C63) -> 53981 | D67: =AVERAGE(D59:D63) -> 56000.6 | E67: =AVERAGE(E59:E63) -> 2152.2 | F67: =AVERAGE(F59:F63) -> 25.109763 | G67: =AVERAGE(G59:G63) -> 37.3
B69: COMPS-IMPLIED JB VALUATION
B70: JB LTM EBITDA | C70: =E65 -> 1195
B71: Median Peer EV/EBITDA | C71: =F66 -> 23.760486
B72: Mean Peer EV/EBITDA | C72: =F67 -> 25.109763
B73: Implied EV — Median | C73: =C70*C71 -> 28393.78
B74: Implied EV — Mean | C74: =C70*C72 -> 30006.167
B75: (-) Net Debt | C75: ='Summary FootballField'!I11 -> -143.39
B76: Implied Equity — Median | C76: =C73-C75 -> 28537.17
B77: Implied Equity — Mean | C77: =C74-C75 -> 30149.557
B78: Implied Price — Median (₹) | C78: =C76/Assumptions!$C$47 -> 1778.0168
B79: Implied Price — Mean (₹) | C79: =C77/Assumptions!$C$47 -> 1878.4771
A81: # | B81: COMPARABLE COMPS SENSITIVITY ANALYSIS
B82: MEDIAN ↓ | C82: LTM EBITDA ➔
B83: =C78 -> 1778.0168 | C83: 1095 | D83: 1145 | E83: 1195 | F83: 1245 | G83: 1295
B84: 21.8 | C84: 1496.2237 | D84: 1564.1364 | E84: 1632.0492 | F84: 1699.962 | G84: 1767.8748
B85: 22.8 | C85: 1564.448 | D85: 1635.476 | E85: 1706.504 | F85: 1777.5321 | G85: 1848.5601
B86: 23.760486 | C86: 1629.9764 | D86: 1703.9966 | E86: 1778.0168 | F86: 1852.037 | G86: 1926.0573
B87: 24.8 | C87: 1700.8966 | D87: 1778.1551 | E87: 1855.4137 | F87: 1932.6723 | G87: 2009.9308
B88: 25.8 | C88: 1769.1209 | D88: 1849.4947 | E88: 1929.8685 | F88: 2010.2424 | G88: 2090.6162
A91: # | B91: METHOD 3: PRECEDENT TRANSACTIONS
B93: Transaction | C93: Year | D93: EV (₹Cr) | E93: EV/EBITDA | F93: Control Premium%
B94: Zydus Lifesciences acquires Assertio Holdings | C94: 2026 | D94: 1385 | E94: 14.8 | F94: 0.34
B95: Torrent acquires Curatio HC | C95: 2022 | D95: 1885 | E95: 22.4 | F95: 0
B96: Mankind acquires BSV | C96: 2024 | D96: 13630 | E96: 24 | F96: 0
B97: Sun Pharma acquires remaining Taro stake | C97: 2024 | D97: 13336 | E97: 24.7 | F97: 0.48
B98: Ipca Laboratories acquires Unichem Laboratories | C98: 2023 | D98: 1840 | E98: 22.1 | F98: 0.33
B100: MEDIAN | C100: - | D100: =MEDIAN(D94:D98) -> 1885 | E100: =J116 -> 22.4 | F100: =MEDIAN(F94:F98) -> 0.33
B101: Torrent / JB (THIS DEAL) | C101: 2025 | D101: ='Deal Mechanics'!C35 -> 25680 | E101: 22.7 | F101: -
B103: JB LTM EBITDA | C103: =E65 -> 1195
B104: Median Precedent EV/EBITDA | C104: =E100 -> 22.4
B105: Control Premium | C105: =J115 -> 0
B106: Precedent Implied EV (incl. control prem) | C106: =C103*C104*(1+C105) -> 26768
B107: (-) Net Debt | C107: ='Summary FootballField'!I11 -> -143.39
B108: Implied Equity Value (₹ Cr) | C108: =C106-C107 -> 26911.39
B109: Implied Price/Share (₹) | C109: =C108/Assumptions!$C$47 -> 1676.7221
B111: PRECEDENT SENSITIVITY ANALYSIS
B112: MEDIAN EV/EBITDA ↓ | C112: CONTROL PREMIUM ➔
B113: =C109 -> 1676.7221 | C113: 0 | D113: 0.1 | E113: 0.2 | F113: 0.3 | G113: 0.4
B114: 20.4 | C114: 1527.8125 | D114: 1679.7003 | E114: 1831.5882 | F114: 1983.476 | G114: 2135.3639
B115: 21.4 | C115: 1602.2673 | D115: 1761.6006 | E115: 1920.934 | F115: 2080.2673 | G115: 2239.6006 | J115: 0
B116: 22.4 | C116: 1676.7221 | D116: 1843.5009 | E116: 2010.2798 | F116: 2177.0586 | G116: 2343.8374 | J116: 22.4
B117: 24.4 | C117: 1825.6318 | D117: 2007.3016 | E117: 2188.9713 | F117: 2370.6411 | G117: 2552.3109

Sheet Summary FootballField
B1: EXECUTIVE SUMMARY & FOOTBALL FIELD VALUATION
B2: Torrent Pharmaceuticals — Acquisition of J.B. Chemicals & Pharmaceuticals
A4: # | B4: DEAL SNAPSHOT | G4: KEY FINANCIAL METRICS (FY25 STANDALONE)
B5: Acquirer | C5: Torrent Pharmaceuticals Ltd | H5: Torrent | I5: JB Chem | J5: Combined
B6: Target | C6: J.B. Chemicals & Pharmaceuticals Ltd | G6: Revenue | H6: ='Standalone Torrent'!E6 -> 11516 | I6: ='Standalone JBChem'!E6 -> 3918 | J6: =H6+I6 -> 15434
B7: Deal Type | C7: SPA (46.39%) + Open Offer (26%) + Merger | G7: EBITDA | H7: ='Standalone Torrent'!E8 -> 3721 | I7: ='Standalone JBChem'!E10 -> 1087 | J7: =H7+I7 -> 4808
B8: Headline EV | C8: ₹25,689 Crores | G8: EBITDA Margin | H8: ='Standalone Torrent'!E9 -> 0.323 | I8: ='Standalone JBChem'!E11 -> 0.27743747 | J8: =J7/J6 -> 0.31152002
B9: SPA Price | C9: ₹1,600 / share (KKR exit) | G9: PAT | H9: ='Standalone Torrent'!E16 -> 1911.195 | I9: ='Standalone JBChem'!E18 -> 698.022 | J9: =(H9+I9)-((Assumptions!C55*(1-Assumptions!F32))) -> 1915.717
B10: Open Offer Price | C10: ₹1,639.18 / share | G10: EPS (₹) | H10: ='Standalone Torrent'!E17 -> 56.47 | I10: ='Standalone JBChem'!E20 -> 42.37 | J10: =J9/'Deal Mechanics'!C51 -> 50.535698
B11: Merger Swap | C11: 51 Torrent shares per 100 JB shares | G11: Net Debt | H11: 2245.54 | I11: -143.39 | J11: =H11+I11+Assumptions!C53 -> 14602.15
B12: Financing | C12: ₹12,500Cr NCD @ 7.6% | G12: Mkt Cap | H12: 150000 | I12: 35000 | J12: =H12+I12 -> 185000
B13: Implied EV/EBITDA | C13: ~22x FY26E (mgmt guided) | G13: IPM Rank | H13: 7 | I13: — | J13: Top 2-3
B14: Synergy Target | C14: ₹400-450Cr p.a. (3-yr ramp)
A17: # | B17: FOOTBALL FIELD — IMPLIED JB EQUITY VALUE (₹ Crores)
B18: Methodology | C18: Low | D18: Mid | E18: High | F18: Impl. Price Low (₹) | G18: Impl. Price High (₹) | H18: Deal Price (₹) | I18: Helper Column
B19: 52-Week Mkt Range | C19: =F19*Assumptions!$C$47 -> 22149 | D19: =AVERAGE(C19,E19) -> 27525.75 | E19: =G19*Assumptions!$C$47 -> 32902.5 | F19: 1380 | G19: 2050 | H19: =Assumptions!$C$48 -> 1600 | I19: =E19-C19 -> 10753.5
B20: DCF — Bear (11.5% WACC and 16x) | C20: =F20*Assumptions!$C$47 -> 23750.324 | D20: =AVERAGE(E20,C20) -> 24375.585 | E20: =G20*Assumptions!$C$47 -> 25000.846 | F20: =Valuation!C52 -> 1479.771 | G20: =Valuation!D52 -> 1557.6851 | H20: =Assumptions!$C$48 -> 1600 | I20: =E20-C20 -> 1250.5217
B21: DCF — Base (10.7% WACC) | C21: =F21*Assumptions!$C$47 -> 25806.999 | D21: =AVERAGE(C21,E21) -> 27101.149 | E21: =G21*Assumptions!$C$47 -> 28395.298 | F21: =Valuation!D51 -> 1607.9127 | G21: =Valuation!F51 -> 1769.1775 | H21: =Assumptions!$C$48 -> 1600 | I21: =E21-C21 -> 2588.2993
B22: DCF — Bull (9.7% WACC) | C22: =F22*Assumptions!$C$47 -> 29671.684 | D22: =AVERAGE(C22,E22) -> 30349.954 | E22: =G22*Assumptions!$C$47 -> 31028.223 | F22: =Valuation!F49 -> 1848.703 | G22: =Valuation!G49 -> 1933.2226 | H22: =Assumptions!$C$48 -> 1600 | I22: =E22-C22 -> 1356.5394
B23: Comps — Bear | C23: =F23*Assumptions!$C$47 -> 24014.39 | D23: =AVERAGE(C23,E23) -> 25104.39 | E23: =G23*Assumptions!$C$47 -> 26194.39 | F23: =Valuation!C84 -> 1496.2237 | G23: =Valuation!E84 -> 1632.0492 | H23: =Assumptions!$C$48 -> 1600 | I23: =E23-C23 -> 2180
B24: Comps — Base | C24: =F24*Assumptions!$C$47 -> 27349.146 | D24: =AVERAGE(C24,E24) -> 28537.17 | E24: =G24*Assumptions!$C$47 -> 29725.195 | F24: =Valuation!D86 -> 1703.9966 | G24: =Valuation!F86 -> 1852.037 | H24: =Assumptions!$C$48 -> 1600 | I24: =E24-C24 -> 2376.0486
B25: Comps Bull | C25: =F25*Assumptions!$C$47 -> 29779.39 | D25: =AVERAGE(C25,E25) -> 31019.39 | E25: =G25*Assumptions!$C$47 -> 32259.39 | F25: =Valuation!E87 -> 1855.4137 | G25: =Valuation!G87 -> 2009.9308 | H25: =Assumptions!$C$48 -> 1600 | I25: =E25-C25 -> 2480
B26: Precedents Bear | C26: =F26*Assumptions!$C$47 -> 24521.39 | D26: =AVERAGE(C26,E26) -> 25740.29 | E26: =G26*Assumptions!$C$47 -> 26959.19 | F26: =Valuation!C114 -> 1527.8125 | G26: =Valuation!D114 -> 1679.7003 | H26: =Assumptions!$C$48 -> 1600 | I26: =E26-C26 -> 2437.8
B27: Precedents Base | C27: =F27*Assumptions!$C$47 -> 25716.39 | D27: =AVERAGE(C27,E27) -> 26995.04 | E27: =G27*Assumptions!$C$47 -> 28273.69 | F27: =Valuation!C115 -> 1602.2673 | G27: =Valuation!D115 -> 1761.6006 | H27: =Assumptions!$C$48 -> 1600 | I27: =E27-C27 -> 2557.3
B28: Precedents + 30% ctrl prem (Bull) | C28: =F28*Assumptions!$C$47 -> 34941.79 | D28: =AVERAGE(C28,E28) -> 37953.19 | E28: =G28*Assumptions!$C$47 -> 40964.59 | F28: =Valuation!F116 -> 2177.0586 | G28: =Valuation!G117 -> 2552.3109 | H28: =Assumptions!$C$48 -> 1600 | I28: =E28-C28 -> 6022.8
B29: DEAL VALUATION | C29: ='Deal Mechanics'!C35 -> 25680 | D29: =C29 -> 25680 | E29: =D29 -> 25680 | F29: =Assumptions!C48 -> 1600 | G29: =Assumptions!C49 -> 1639.18 | H29: =Assumptions!C48 -> 1600 | I29: =E29-C29 -> 0
A31: #
B56: The football field analysis indicates that most valuation methodologies value JB Chemicals in the range of ~₹24,000 Cr to ₹31,000 Cr on a standalone basis, while strategic precedent transactions with higher control premiums imply upside beyond ₹35,000 Cr. Torrent’s agreed deal value of ~₹25,700 Cr (₹1,600/share SPA price and ₹1,639 open offer price) lies within the lower to mid end of the overall valuation range, suggesting that the acquisition was executed at a fair and reasonable valuation before considering future synergies. The analysis also highlights that additional value creation potential exists through operational and strategic synergies post-acquisition.
A64: # | B64: COMBINED ENTITY GROWTH TRAJECTORY (₹ Crores)
B65: Metric | C65: FY25A | D65: FY26E | E65: FY27E | F65: FY28E | G65: FY29E | H65: FY30E
B66: Combined Revenue (₹ Cr) | C66: =J6 -> 15434 | D66: ='ProForma Combined'!C9 -> 17424.272 | E66: ='ProForma Combined'!D9 -> 19559.066 | F66: ='ProForma Combined'!E9 -> 22030.74 | G66: ='ProForma Combined'!F9 -> 24525.872 | H66: ='ProForma Combined'!G9 -> 26740.69
B67: Combined EBITDA (₹ Cr) | C67: =J7 -> 4808 | D67: ='ProForma Combined'!C16 -> 5539.5064 | E67: ='ProForma Combined'!D16 -> 6234.9484 | F67: ='ProForma Combined'!E16 -> 7211.0434 | G67: ='ProForma Combined'!F16 -> 8195.4195 | H67: ='ProForma Combined'!G16 -> 8986.084
B68: Combined PAT (₹ Cr) | C68: =J9 -> 1915.717 | D68: ='ProForma Combined'!C27 -> 1568.0108 | E68: ='ProForma Combined'!D27 -> 2052.8012 | F68: ='ProForma Combined'!E27 -> 2774.4712 | G68: ='ProForma Combined'!F27 -> 3550.8537 | H68: ='ProForma Combined'!G27 -> 4205.236
A88: # | B88: EPS (₹) | C88: FY26E | D88: FY27E | E88: FY28E | F88: FY29E | G88: FY30E
B89: Torrent Standalone EPS (₹) | C89: ='Accretion Dilution'!C19 -> 50.746762 | D89: ='Accretion Dilution'!D19 -> 62.639317 | E89: ='Accretion Dilution'!E19 -> 76.555562 | F89: ='Accretion Dilution'!F19 -> 92.48277 | G89: ='Accretion Dilution'!G19 -> 106.69977
B90: Combined Entity EPS (₹) | C90: ='Accretion Dilution'!C20 -> 40.971564 | D90: ='Accretion Dilution'!D20 -> 53.659799 | E90: ='Accretion Dilution'!E20 -> 74.125926 | F90: ='Accretion Dilution'!F20 -> 96.106267 | G90: ='Accretion Dilution'!G20 -> 114.29222
B91: Accretion (%) | C91: =C90/C89-1 -> -0.19262702 | D91: =D90/D89-1 -> -0.14335274 | E91: =E90/E89-1 -> -0.0317369 | F91: =F90/F89-1 -> 0.039180241 | G91: =G90/G89-1 -> 0.071157125
A111: # | B111: STRATEGIC VERDICT & INVESTMENT THESIS
B112: ✅ Strategic Fit & Margin Expansion | C112: JB Chemicals & Pharmaceuticals has a strong and high margin domestic business in therapies like Cardiac and Gastro, which fits well with Torrent Pharmaceuticals’ existing business. JB’s EBITDA margins are expected to improve to around 30% by FY30E, making it a highly profitable and cash generating company. The deal is also expected to create around ₹400 to 450 Cr of cost synergies over 3 years through savings in areas like medical representatives and procurement, which will improve the combined company’s profitability.
B113: ✅ Valuation Triangulation & Margin of Safety | C113: Torrent Pharmaceuticals is buying JB Chemicals & Pharmaceuticals at around ₹1,600 to ₹1,639 per share, which is slightly below JB’s estimated fair value of around ₹1,670 to ₹1,685 per share based on DCF, Comparable Companies and past deals like Curatio and BSV. This means Torrent is acquiring the company at a reasonable price and the expected synergies worth around ₹6,225 Cr become an additional upside benefit for Torrent shareholders.
B114: ✅ Scale & Market Dominance (IPM Rank) | C114: This acquisition is a major step for Torrent Pharmaceuticals, as it moves the company from Rank 7 to among the Top 2 to 3 players in the Indian Pharmaceutical Market (IPM). This larger scale gives Torrent stronger pricing power, better negotiating strength with distributors and pharmacies for shelf space and the potential to receive a higher market valuation like other top pharmaceutical companies.Russia ($20M) + South Africa exposure + medicated lozenges CDMO. A non replicable, high margin B2B platform with global blue chip clients.
B115: ⚠️ Leverage & Dilution Risk (The Headwind) | C115: The deal is expected to reduce Torrent Pharmaceuticals’ EPS by around 19% in FY26E because the company is raising a large ₹12,500 Cr NCD debt at a 7.6% interest rate to finance the acquisition. After the deal, Net Debt/EBITDA will rise sharply to around 3.1x, showing a much higher debt burden. Therefore, successful execution is very important and Torrent must quickly achieve the expected synergies in the first few years to offset the yearly after tax interest cost of around ₹766 Cr and bring the deal back to EPS accretion by FY29.
B116: ⚠️ Valuation Risk (The Multiple) | C116: At around 22x to 23x FY25 EV/EBITDA, the acquisition is being done at a relatively expensive valuation compared to past Indian pharma deals. Because of this, the success of the deal depends heavily on smooth integration and achieving the expected synergies. Torrent Pharmaceuticals needs to achieve at least 75% of the projected ₹400 to 450 Cr synergies just to avoid EPS dilution. If the synergies are delayed or lower than expected during the 3 year integration period, shareholders may face longer EPS dilution and pressure on the stock price.
B117: 📌 Final Conclusion (The Verdict) | C117: DEAL IS STRATEGICALLY COMPELLING AND FINANCIALLY JUSTIFIABLE. While the upfront leverage and EPS dilution are real near term headwinds, the strategic acquisition of JB's high growth portfolio at a discount to its intrinsic standalone value (₹1,670-₹1,685) creates a massive margin of safety. If management successfully executes the ~₹6,225 Cr synergy plan, the deal will rapidly deleverage and deliver immense long term value creation for Torrent shareholders.
